Workbook

Sheet Sheet1
C1: 2005 | D1: 2006 | E1: 2007 | F1: 2008
B2: Revenues | C2: 100 | D2: 125 | E2: 150 | F2: 175
B3: Cost of Goods Sold | C3: 50 | D3: 60 | E3: 70 | F3: 80
B4: Groos Profit | C4: =C2-C3 -> 50 | D4: =D2-D3 -> 65 | E4: =E2-E3 -> 80 | F4: =F2-F3 -> 95

Sheet Income Statement
A1: Income Statement | C1: 2004 | D1: 2005 | E1: 2006 | F1: 2007 | G1: 2008
B2: Revenues | C2: 800 | D2: 1000 | E2: 1500 | F2: 2500 | G2: 4500
B3: Cost of Hoods Sold | C3: 300 | D3: 500 | E3: 1200 | F3: 3400 | G3: 4000
B4: Gross Profit | C4: =C2-C3 -> 500 | D4: =D2-D3 -> 500 | E4: =E2-E3 -> 300 | F4: =F2-F3 -> -900 | G4: =G2-G3 -> 500
B5: Operating Costs | C5: 35 | D5: 45 | E5: 55 | F5: 65 | G5: 78
B6: Non-operating Costs | C6: 15 | D6: 15 | E6: 15 | F6: 15 | G6: 15
B7: Pre-Tax Profit | C7: =C4-C5-C6 -> 450 | D7: =D4-D5-D6 -> 440 | E7: =E4-E5-E6 -> 230 | F7: =F4-F5-F6 -> -980 | G7: =G4-G5-G6 -> 407
B8: Tax | C8: =C7*$C$11 -> 157.5 | D8: =D7*$C$11 -> 154 | E8: =E7*$C$11 -> 80.5 | F8: =F7*$C$11 -> -343 | G8: =G7*$C$11 -> 142.45
B9: Net Income | C9: =C7-C8 -> 292.5 | D9: =D7-D8 -> 286 | E9: =E7-E8 -> 149.5 | F9: =F7-F8 -> -637 | G9: =G7-G8 -> 264.55
B11: Tax Rate | C11: 0.35

Sheet Sheet3
B1: Income Statement | C1: 2005 | D1: 2006 | E1: 2007 | F1: 2008
B2: Revenues | C2: =Sheet1!C2+'Income Statement'!D2 -> 1100 | D2: =Sheet1!D2+'Income Statement'!E2 -> 1625 | E2: =Sheet1!E2+'Income Statement'!F2 -> 2650 | F2: =Sheet1!F2+'Income Statement'!G2 -> 4675 | G2: =SUM(C2:F2) -> 10050
B3: Cost of Hoods Sold | C3: =Sheet1!C3+'Income Statement'!D3 -> 550 | D3: =Sheet1!D3+'Income Statement'!E3 -> 1260 | E3: =Sheet1!E3+'Income Statement'!F3 -> 3470 | F3: =Sheet1!F3+'Income Statement'!G3 -> 4080
B4: Gross Profit | C4: =C2-C3 -> 550 | D4: =D2-D3 -> 365 | E4: =E2-E3 -> -820 | F4: =F2-F3 -> 595 | G4: =AVERAGE(C4:F4) -> 172.5

Sheet Errors
A1: =2/0 -> #DIV/0! | B1: Divided by Zero
A3: =#REF!*#REF! -> #REF! | B3: Refernceing Error
A5: =10^800 -> #NUM! | B5: Number not Valid
A7: {=4*hi} -> #NAME? | B7: Text Not Valid
A9: =D9+E9 -> #VALUE! | B9: Incorrect Arguments | D9: Hi | E9: 5
