Workbook
Name COGS2004: 'Income Statement'!$C$6
Name COGS2004: '[1]Income Statement'!$C$6
Name COGS2004: '[1]Income Statement'!$C$6
Name COGS2004: '[1]Income Statement'!$C$6
Name COGS2004: [2]Sheet2!$C$6
Name GP: 'Income Statement'!$C$7
Name Revenues2004: 'Income Statement'!$C$5
Name Revenues2004: '[1]Income Statement'!$C$5
Name Revenues2004: '[1]Income Statement'!$C$5
Name Revenues2004: '[1]Income Statement'!$C$5
Name Revenues2004: [2]Sheet2!$C$5

Sheet Sheet1
C1: Historicals | E1: Forecasts
A2: Income Statement | C2: 2005 | D2: 2006 | E2: 2007 | F2: 2008
B3: Revenues | C3: 100 | D3: 125 | E3: 150 | F3: 175
B4: Cost of Goods Sold | C4: 50 | D4: 60 | E4: 70 | F4: 80
B5: Gross Profit | C5: =C3-C4 -> 50 | D5: =D3-D4 -> 65 | E5: =E3-E4 -> 80 | F5: =F3-F4 -> 95

Sheet Income Statement
B1: Enter company name: | C1: Lemonade Co.
B3: ="Income Statement for "&C1 -> Income Statement for Lemonade Co. | H3: 43723
C4: 42004 | D4: =DATE(YEAR(C4)+1,MONTH(C4),DAY(C4)) -> 42369 | E4: =DATE(YEAR(D4)+1,MONTH(D4),DAY(D4)) -> 42735 | F4: =DATE(YEAR(E4)+1,MONTH(E4),DAY(E4)) -> 43100 | G4: =DATE(YEAR(F4)+1,MONTH(F4),DAY(F4)) -> 43465 | H4: =YEARFRAC(G4,H3) -> 0.70833333
B5: Revenues | C5: 800 | D5: 1000 | E5: 1500 | F5: 2500 | G5: 4500 | H5: =G5*H4 -> 3187.5
B6: Cost of Goods Sold | C6: 300 | D6: 500 | E6: 1200 | F6: 3400 | G6: 4000
B7: Gross Profit | C7: =Revenues2004-COGS2004 -> 500 | D7: =D5-D6 -> 500 | E7: =E5-E6 -> 300 | F7: =F5-F6 -> -900 | G7: =G5-G6 -> 500
B8: Operating costs | C8: 35 | D8: 45 | E8: 55 | F8: 65 | G8: 78
B9: Non-operating costs | C9: 15 | D9: 15 | E9: 15 | F9: 15 | G9: 15
B10: Pretax profit | C10: =C7-C8-C9 -> 450 | D10: =D7-D8-D9 -> 440 | E10: =E7-E8-E9 -> 230 | F10: =F7-F8-F9 -> -980 | G10: =G7-G8-G9 -> 407
B11: Tax | C11: =IF($C$14,C10*$C14,"No tax") -> 157.5 | D11: =IF($C$14,D10*$C14,"No tax") -> 154 | E11: =IF($C$14,E10*$C14,"No tax") -> 80.5 | F11: =IF($C$14,F10*$C14,"No tax") -> -343 | G11: =IF($C$14,G10*$C14,"No tax") -> 142.45
B12: Net income | C12: =IFERROR(C10-C11,"NM") -> 292.5 | D12: =IFERROR(D10-D11,"NM") -> 286 | E12: =IFERROR(E10-E11,"NM") -> 149.5 | F12: =IFERROR(F10-F11,"NM") -> -637 | G12: =IFERROR(G10-G11,"NM") -> 264.55
B14: Tax rate | C14: 0.35
B16: Override | D16: 5000
B17: Model-derived value (5x pretax profit): | D17: =IF(D16,D16,C10*5) -> 5000

Sheet IF
B1: Question 1
B2: Input:
B3: Input your age: | C3: 25
B4: Input your younger sibling's age: | C4: 17
B6: Question | C6: Answer
B7: Can you vote for president?
B8: For how many years have you been eligible to vote?
B9: Are both me and my younger sibling eligible to vote?
B11: Question 2
B12: Input:
B13: Input expected company revenue: | C13: 300
B14: Input actual company revenue: | C14: 400
B16: Input expected company EBITDA: | C16: 50
B17: Input actual company EBITDA: | C17: 60
B19: Question | C19: Answer
B20: Did the company exceed revenue expectations?
B21: Did the company exceed both revenue and EBITDA expectations?

Sheet IF_ans
B1: Question 1
B2: Input:
B3: Input your age: | C3: 25
B4: Input your younger sibling's age: | C4: 17
B6: Question | C6: Answer
B7: Can you vote for president? | C7: =IF(C3>=18,"yes","no") -> yes
B8: For how many years have you been eligible to vote? | C8: =IF(C7="yes",C3-18,0) -> 7
B9: Are both me and my younger sibling eligible to vote? | C9: =IF(C7="yes",IF(C4>=18,"yes","no"),"no") -> no | D9: =IF(AND(C7="yes",C4>=18),"yes","no") -> no
B11: Question 2
B12: Input:
B13: Input expected company revenue: | C13: 300
B14: Input actual company revenue: | C14: 400
B16: Input expected company EBITDA: | C16: 50
B17: Input actual company EBITDA: | C17: 60
B19: Question | C19: Answer
B20: Did the company exceed revenue expectations? | C20: =IF(C14>C13,"yes","no") -> yes
B21: Did the company exceed both revenue and EBITDA expectations? | C21: =IF(AND(C20="yes",C17>C16),"yes","no") -> yes

Sheet IFS
B2: Select a driver for operating expense forecasts | H2: 1
C3: Actual | F3: Forecasts
C4: 2013 | D4: 2014 | E4: 2015 | F4: 2016 | G4: 2016 | H4: 2016
B5: Revenue | C5: 1376 | D5: 1487 | E5: 1532 | F5: =E5*(1+F12) -> 1577.96 | G5: =F5*(1+G12) -> 1625.2988 | H5: =G5*(1+H12) -> 1674.0578
B6: Cost of sales | C6: 467 | D6: 540 | E6: 564 | F6: =F5*F13 -> 583.8452 | G6: =G5*G13 -> 601.36056 | H6: =H5*H13 -> 619.40137
B7: Gross Profit | C7: =C5-C6 -> 909 | D7: =D5-D6 -> 947 | E7: =E5-E6 -> 968 | F7: =F5-F6 -> 994.1148 | G7: =G5-G6 -> 1023.9382 | H7: =H5-H6 -> 1054.6564
B8: Operating expenses | C8: 121 | D8: 146 | E8: 167 | F8: =F5*F14 -> 172.01 | G8: =G5*G14 -> 177.1703 | H8: =H5*H14 -> 182.48541
B9: Operating profit | C9: =C7-C8 -> 788 | D9: =D7-D8 -> 801 | E9: =E7-E8 -> 801 | F9: =F7-F8 -> 822.1048 | G9: =G7-G8 -> 846.76794 | H9: =H7-H8 -> 872.17098
B11: Assumptions
B12: Revenue growth | D12: =D5/C5-1 -> 0.080668605 | E12: =E5/D5-1 -> 0.030262273 | F12: 0.03 | G12: 0.03 | H12: 0.03
B13: Cost of sales margin | C13: =C6/C5 -> 0.33938953 | D13: =D6/D5 -> 0.36314728 | E13: =E6/E5 -> 0.36814621 | F13: 0.37 | G13: 0.37 | H13: 0.37
B14: Operating expenses margin (Nested IF) | C14: =C8/C5 -> 0.087936047 | D14: =D8/D5 -> 0.098184264 | E14: =E8/E5 -> 0.10900783 | F14: =IF($H$2=1,E14,IF($H$2=2,AVERAGE(C14:E14),IF($H$2=3,AVERAGE(D14:E14),E8/F5))) -> 0.10900783 | G14: =IF($H$2=1,F14,IF($H$2=2,AVERAGE(D14:F14),IF($H$2=3,AVERAGE(E14:F14),F8/G5))) -> 0.10900783 | H14: =IF($H$2=1,G14,IF($H$2=2,AVERAGE(E14:G14),IF($H$2=3,AVERAGE(F14:G14),G8/H5))) -> 0.10900783
B15: Operating expenses margin (with IFS - 2016 Only)
B16: Operating expenses forecast drivers
B17: 1 = Apply last year's operating expense margin
B18: 2 = Apply last 3 years' average operating expense margin
B19: 3 = Apply last 2 years' average operating expense margin
B20: If no driver is selected, keep operating expenses flat

Sheet IFS_ans
B2: Select a driver for operating expense forecasts | H2: 1
C3: Actual | F3: Forecasts
C4: 2013 | D4: 2014 | E4: 2015 | F4: 2016 | G4: 2016 | H4: 2016
B5: Revenue | C5: 1376 | D5: 1487 | E5: 1532 | F5: =E5*(1+F12) -> 1577.96 | G5: =F5*(1+G12) -> 1625.2988 | H5: =G5*(1+H12) -> 1674.0578
B6: Cost of sales | C6: 467 | D6: 540 | E6: 564 | F6: =F5*F13 -> 583.8452 | G6: =G5*G13 -> 601.36056 | H6: =H5*H13 -> 619.40137
B7: Gross Profit | C7: =C5-C6 -> 909 | D7: =D5-D6 -> 947 | E7: =E5-E6 -> 968 | F7: =F5-F6 -> 994.1148 | G7: =G5-G6 -> 1023.9382 | H7: =H5-H6 -> 1054.6564
B8: Operating expenses | C8: 121 | D8: 146 | E8: 167 | F8: =F5*F14 -> 172.01 | G8: =G5*G14 -> 177.1703 | H8: =H5*H14 -> 182.48541
B9: Operating profit | C9: =C7-C8 -> 788 | D9: =D7-D8 -> 801 | E9: =E7-E8 -> 801 | F9: =F7-F8 -> 822.1048 | G9: =G7-G8 -> 846.76794 | H9: =H7-H8 -> 872.17098
B11: Assumptions
B12: Revenue growth | D12: =D5/C5-1 -> 0.080668605 | E12: =E5/D5-1 -> 0.030262273 | F12: 0.03 | G12: 0.03 | H12: 0.03
B13: Cost of sales margin | C13: =C6/C5 -> 0.33938953 | D13: =D6/D5 -> 0.36314728 | E13: =E6/E5 -> 0.36814621 | F13: 0.37 | G13: 0.37 | H13: 0.37
B14: Operating expenses margin (Nested IF) | C14: =C8/C5 -> 0.087936047 | D14: =D8/D5 -> 0.098184264 | E14: =E8/E5 -> 0.10900783 | F14: =IF($H$2=1,E14,IF($H$2=2,AVERAGE(C14:E14),IF($H$2=3,AVERAGE(D14:E14),E8/F5))) -> 0.10900783 | G14: =IF($H$2=1,F14,IF($H$2=2,AVERAGE(D14:F14),IF($H$2=3,AVERAGE(E14:F14),F8/G5))) -> 0.10900783 | H14: =IF($H$2=1,G14,IF($H$2=2,AVERAGE(E14:G14),IF($H$2=3,AVERAGE(F14:G14),G8/H5))) -> 0.10900783
B15: Operating expenses margin (with IFS - 2016 Only) | F15: =_xlfn.IFS($H$2=1,E14,$H$2=2,AVERAGE(C14:E14),$H$2=3,AVERAGE(D14:E14),TRUE,E8/F5) -> 0.10900783 | G15: =_xlfn.IFS($H$2=1,F14,$H$2=2,AVERAGE(D14:F14),$H$2=3,AVERAGE(E14:F14),TRUE,F8/G5) -> 0.10900783 | H15: =_xlfn.IFS($H$2=1,G14,$H$2=2,AVERAGE(E14:G14),$H$2=3,AVERAGE(F14:G14),TRUE,G8/H5) -> 0.10900783
B16: Operating expenses forecast drivers
B17: 1 = Apply last year's operating expense margin
B18: 2 = Apply last 3 years' average operating expense margin
B19: 3 = Apply last 2 years' average operating expense margin
B20: If no driver is selected, keep operating expenses flat

Sheet IFERROR
C2: 2014 | D2: =C2+1 -> 2015 | E2: =D2+1 -> 2016
B3: Net earnings | C3: 1500 | D3: 1850 | E3: 2130
B4: Shares outstanding | C4: 0 | D4: 50 | E4: 75
B5: Earnings per share (EPS)

Sheet IFERROR_ans
C2: 2014 | D2: =C2+1 -> 2015 | E2: =D2+1 -> 2016
B3: Net earnings | C3: 1500 | D3: 1850 | E3: 2130
B4: Shares outstanding | C4: 0 | D4: 50 | E4: 75
B5: Earnings per share (EPS) | C5: =IFERROR(C3/C4,"NM") -> NM | D5: =IFERROR(D3/D4,"NM") -> 37 | E5: =IFERROR(E3/E4,"NM") -> 28.4

Sheet AND OR
B1: Combine IF and AND functions to answer this question:
C2: Criteria: If on the job 5 years or more AND received an 8 or higher for a performance rating, output a salary reflecting a 5% raise, otherwise, output "No raise"
C3: Employee | D3: Age | E3: Salary | F3: Years at Company | G3: Performance Rating | H3: New salary
C4: A | D4: 25 | E4: 53140 | F4: 0 | G4: 10
C5: B | D5: 48 | E5: 110662 | F5: 11 | G5: 2
C6: C | D6: 48 | E6: 117294 | F6: 17 | G6: 8
C7: D | D7: 34 | E7: 114373 | F7: 19 | G7: 10
B9: Combine IF and OR functions to answer this question:
C10: Criteria: If on the job 5 years or more OR received an 8 or higher for a performance rating, output a salary reflecting a 5% raise, otherwise, output "No raise"
C11: Employee | D11: Age | E11: Salary | F11: Years at Company | G11: Performance Rating | H11: New salary
C12: A | D12: 25 | E12: 53140 | F12: 0 | G12: 10
C13: B | D13: 48 | E13: 110662 | F13: 11 | G13: 2
C14: C | D14: 48 | E14: 117294 | F14: 17 | G14: 8
C15: D | D15: 34 | E15: 114373 | F15: 19 | G15: 10

Sheet AND OR _ans
B1: Combine IF and AND functions to answer this question:
C2: Criteria: If on the job 5 years or more AND received an 8 or higher for a performance rating, output a salary reflecting a 5% raise, otherwise, output "No raise"
C3: Employee | D3: Age | E3: Salary | F3: Years at Company | G3: Performance Rating | H3: New salary
C4: A | D4: 25 | E4: 53140 | F4: 0 | G4: 10 | H4: =IF(AND(F4>5,G4>=8),E4*1.05,"No raise") -> No raise
C5: B | D5: 48 | E5: 110662 | F5: 11 | G5: 2 | H5: =IF(AND(F5>5,G5>=8),E5*1.05,"No raise") -> No raise
C6: C | D6: 48 | E6: 117294 | F6: 17 | G6: 8 | H6: =IF(AND(F6>5,G6>=8),E6*1.05,"No raise") -> 123158.7
C7: D | D7: 34 | E7: 114373 | F7: 19 | G7: 10 | H7: =IF(AND(F7>5,G7>=8),E7*1.05,"No raise") -> 120091.65
B9: Combine IF and OR functions to answer this question:
C10: Criteria: If on the job 5 years or more OR received an 8 or higher for a performance rating, output a salary reflecting a 5% raise, otherwise, output "No raise"
C11: Employee | D11: Age | E11: Salary | F11: Years at Company | G11: Performance Rating | H11: New salary
C12: A | D12: 25 | E12: 53140 | F12: 0 | G12: 10 | H12: =IF(OR(F12>5,G12>=8),E12*1.05,"No raise") -> 55797
C13: B | D13: 48 | E13: 110662 | F13: 11 | G13: 2 | H13: =IF(OR(F13>5,G13>=8),E13*1.05,"No raise") -> 116195.1
C14: C | D14: 48 | E14: 117294 | F14: 17 | G14: 8 | H14: =IF(OR(F14>5,G14>=8),E14*1.05,"No raise") -> 123158.7
C15: D | D15: 34 | E15: 114373 | F15: 19 | G15: 10 | H15: =IF(OR(F15>5,G15>=8),E15*1.05,"No raise") -> 120091.65

Sheet Reference, ROWS, COLUMNS
A1: Income Statement | C1: 2005 | D1: 2006 | E1: 2007 | F1: 2008
B2: Revenues | C2: =Sheet1!C3+'Income Statement'!D5 -> 1100 | D2: =Sheet1!D3+'Income Statement'!E5 -> 1625 | E2: =Sheet1!E3+'Income Statement'!F5 -> 2650 | F2: =Sheet1!F3+'Income Statement'!G5 -> 4675
B3: Cost of Goods Sold | C3: =Sheet1!C4+'Income Statement'!D6 -> 550 | D3: =Sheet1!D4+'Income Statement'!E6 -> 1260 | E3: =Sheet1!E4+'Income Statement'!F6 -> 3470 | F3: =Sheet1!F4+'Income Statement'!G6 -> 4080
B4: Gross Profit | C4: =C2-C3 -> 550 | D4: =D2-D3 -> 365 | E4: =E2-E3 -> -820 | F4: =F2-F3 -> 595
B6: Input a year: | C6: 2006
C8: Gross Profit
B9: HLOOKUP
B10: INDEX
B11: CHOOSE
B12: OFFSET
B14: Input a metric: | C14: Revenues
C16: Output 2008 results for the selected metric:
B17: VLOOKUP

Sheet Reference, ROWS, COLUMNS_ans
A1: Income Statement | C1: 2005 | D1: 2006 | E1: 2007 | F1: 2008
B2: Revenues | C2: =Sheet1!C3+'Income Statement'!D5 -> 1100 | D2: =Sheet1!D3+'Income Statement'!E5 -> 1625 | E2: =Sheet1!E3+'Income Statement'!F5 -> 2650 | F2: =Sheet1!F3+'Income Statement'!G5 -> 4675
B3: Cost of Goods Sold | C3: =Sheet1!C4+'Income Statement'!D6 -> 550 | D3: =Sheet1!D4+'Income Statement'!E6 -> 1260 | E3: =Sheet1!E4+'Income Statement'!F6 -> 3470 | F3: =Sheet1!F4+'Income Statement'!G6 -> 4080
B4: Gross Profit | C4: =C2-C3 -> 550 | D4: =D2-D3 -> 365 | E4: =E2-E3 -> -820 | F4: =F2-F3 -> 595
B6: Input a year: | C6: 2006
C8: Gross Profit
B9: HLOOKUP | C9: =HLOOKUP(C6,B1:F4,ROW()-5,0) -> 365 | F9: =COLUMN(H6) -> 8
B10: INDEX | C10: =INDEX(B1:F4,ROW(C4),COLUMN(D4)-1) -> 365 | F10: =ROW(H7) -> 7
B11: CHOOSE | C11: =CHOOSE(2,C4,D4,E4,F4) -> 365 | F11: =ROWS(1:4) -> 4
B12: OFFSET | C12: =OFFSET(B1,ROW(B4)-1,COLUMN(D4)-2) -> 365 | F12: =COLUMNS(A:C) -> 3
B14: Input a metric: | C14: Revenues
C16: Output 2008 results for the selected metric:
B17: VLOOKUP | C17: =VLOOKUP(C14,B1:F4,COLUMN(F1)-1,0) -> 4675

Sheet Lookup & Reference
B2: Input Company Name: | C2: Lemonade Co.
B3: Tax rate | C3: 0.35
B4: ="Income Statement for "&C2 -> Income Statement for Lemonade Co.
C5: 42004 | D5: =EOMONTH(C5,12) -> 42369 | E5: =EOMONTH(D5,12) -> 42735 | F5: =EOMONTH(E5,12) -> 43100 | G5: =EOMONTH(F5,12) -> 43465
B6: Revenues | C6: 800 | D6: 1000 | E6: 1500 | F6: 2500 | G6: 4500
B7: Cost of Goods Sold | C7: 300 | D7: 500 | E7: 1200 | F7: 3400 | G7: 4000
B8: Gross Profit | C8: =C6-C7 -> 500 | D8: =D6-D7 -> 500 | E8: =E6-E7 -> 300 | F8: =F6-F7 -> -900 | G8: =G6-G7 -> 500 | K8: MATCH - the third argument - match type
B9: Operating costs | C9: 35 | D9: 45 | E9: 55 | F9: 65 | G9: 78 | K9: 0 = Exact match. You'll almost always input 0 for an exact match.
B10: Pretax Profit | C10: =C8-C9 -> 465 | D10: =D8-D9 -> 455 | E10: =E8-E9 -> 245 | F10: =F8-F9 -> -965 | G10: =G8-G9 -> 422 | K10: 1 or omitted = Excel will find the largest value that is less than or equal to the lookup value, as long as data is in ascending order
B11: Taxes | C11: =C10*$C$4 -> 0 | D11: =D10*$C$4 -> 0 | E11: =E10*$C$4 -> 0 | F11: =F10*$C$4 -> 0 | G11: =G10*$C$4 -> 0 | K11: -1 = Excel will find the smallest value that is greater than or equal to the lookup value as long as data is in descending order
B12: Net Profit | C12: =C10-C11 -> 465 | D12: =D10-D11 -> 455 | E12: =E10-E11 -> 245 | F12: =F10-F11 -> -965 | G12: =G10-G11 -> 422
B13: Basic Shares Outstanding | C13: 100 | D13: 110 | E13: 115 | F13: 120 | G13: 125 | K13: HLOOKUP / VLOOKUP - the fourth argument - range lookup
B14: Basic EPS | C14: =IFERROR(C12/C13,"NM") -> 4.65 | D14: =IFERROR(D12/D13,"NM") -> 4.1363636 | E14: =IFERROR(E12/E13,"NM") -> 2.1304348 | F14: =IFERROR(F12/F13,"NM") -> -8.0416667 | G14: =IFERROR(G12/G13,"NM") -> 3.376 | K14: TRUE (1 or omitted): If an exact match is not found, the next largest value that is less than lookup_value is returned.
K15: FALSE (0): Only an exact match will be returned. If no exact match, will return #N/A
B16: Exit year | C16: 42735 | K16: Important: For text lookups, an exact match (0) is required
B17: Select a metric: | C17: Gross Profit
B20: Solution: Combining formulas to make more durable formulas without hardcoding
AC21: 2014 | AD21: =AC21+1 -> 2015 | AE21: =AD21+1 -> 2016 | AF21: =AE21+1 -> 2017 | AG21: =AF21+1 -> 2018
D22: Accomplish using:
B23: Combination formulas: | D23: HLOOKUP w/ MATCH | AD23: Output: | AE23: =MATCH(#REF!,AC21:AG21,0) -> #REF! | AF23: <---- =MATCH(AE23,AC21:AG21,0)
D24: VLOOKUP w/MATCH
D25: OFFSET w/ MATCH
D26: INDEX w/ MATCH
D27: CHOOSE w/ MATCH

Sheet Lookup & Reference_ans
B2: Input Company Name: | C2: Lemonade Co.
B3: Tax rate | C3: 0.35
B4: ="Income Statement for "&C2 -> Income Statement for Lemonade Co.
C5: 42004 | D5: =EOMONTH(C5,12) -> 42369 | E5: =EOMONTH(D5,12) -> 42735 | F5: =EOMONTH(E5,12) -> 43100 | G5: =EOMONTH(F5,12) -> 43465
B6: Revenues | C6: 800 | D6: 1000 | E6: 1500 | F6: 2500 | G6: 4500
B7: Cost of Goods Sold | C7: 300 | D7: 500 | E7: 1200 | F7: 3400 | G7: 4000
B8: Gross Profit | C8: =C6-C7 -> 500 | D8: =D6-D7 -> 500 | E8: =E6-E7 -> 300 | F8: =F6-F7 -> -900 | G8: =G6-G7 -> 500 | K8: MATCH - the third argument - match type
B9: Operating costs | C9: 35 | D9: 45 | E9: 55 | F9: 65 | G9: 78 | K9: 0 = Exact match. You'll almost always input 0 for an exact match.
B10: Pretax Profit | C10: =C8-C9 -> 465 | D10: =D8-D9 -> 455 | E10: =E8-E9 -> 245 | F10: =F8-F9 -> -965 | G10: =G8-G9 -> 422 | K10: 1 or omitted = Excel will find the largest value that is less than or equal to the lookup value, as long as data is in ascending order
B11: Taxes | C11: =C10*$C$4 -> 0 | D11: =D10*$C$4 -> 0 | E11: =E10*$C$4 -> 0 | F11: =F10*$C$4 -> 0 | G11: =G10*$C$4 -> 0 | K11: -1 = Excel will find the smallest value that is greater than or equal to the lookup value as long as data is in descending order
B12: Net Profit | C12: =C10-C11 -> 465 | D12: =D10-D11 -> 455 | E12: =E10-E11 -> 245 | F12: =F10-F11 -> -965 | G12: =G10-G11 -> 422
B13: Basic Shares Outstanding | C13: 100 | D13: 110 | E13: 115 | F13: 120 | G13: 125 | K13: HLOOKUP / VLOOKUP - the fourth argument - range lookup
B14: Basic EPS | C14: =IFERROR(C12/C13,"NM") -> 4.65 | D14: =IFERROR(D12/D13,"NM") -> 4.1363636 | E14: =IFERROR(E12/E13,"NM") -> 2.1304348 | F14: =IFERROR(F12/F13,"NM") -> -8.0416667 | G14: =IFERROR(G12/G13,"NM") -> 3.376 | K14: TRUE (1 or omitted): If an exact match is not found, the next largest value that is less than lookup_value is returned.
K15: FALSE (0): Only an exact match will be returned. If no exact match, will return #N/A
B16: Exit year | C16: 42735 | K16: Important: For text lookups, an exact match (0) is required
B17: Select a metric: | C17: Gross Profit
B20: Solution: Combining formulas to make more durable formulas without hardcoding
AC21: 2014 | AD21: =AC21+1 -> 2015 | AE21: =AD21+1 -> 2016 | AF21: =AE21+1 -> 2017 | AG21: =AF21+1 -> 2018
D22: Accomplish using:
B23: Combination formulas: | C23: =HLOOKUP(C16,B5:G14,MATCH(C17,B5:B14,0)) -> 300 | D23: HLOOKUP w/ MATCH | AD23: Output: | AE23: =MATCH(#REF!,AC21:AG21,0) -> #REF! | AF23: <---- =MATCH(AE23,AC21:AG21,0)
C24: =VLOOKUP(C17,B5:G14,MATCH(C16,B5:G5,0),0) -> 300 | D24: VLOOKUP w/MATCH
C25: =OFFSET(B5,MATCH(C17,B5:B14,0)-1,MATCH(C16,B5:G5,0)-1) -> 300 | D25: OFFSET w/ MATCH
C26: =INDEX(B5:G14,MATCH(C17,B5:B14,0),MATCH(C16,B5:G5,0)) -> 300 | D26: INDEX w/ MATCH
C27: =CHOOSE(MATCH(C16,C5:G5,0),C8,D8,E8,F8,G8) -> 300 | D27: CHOOSE w/ MATCH
C28: =INDIRECT("R"&MATCH(C17,B6:B14,0)+ROWS(B1:B5)&"C"&MATCH(C16,C5:G5,0)+COLUMNS(A5:B5),FALSE) -> 300 | D28: INDIRECT w/MATCH

Sheet Data table
B1: Input Company Name: | C1: Lemonade Co.
B3: ="Income Statement for "&C1 -> Income Statement for Lemonade Co.
C4: Actuals | F4: Projections
C5: 41274 | D5: =EOMONTH(C5,12) -> 41639 | E5: =EOMONTH(D5,12) -> 42004 | F5: =EOMONTH(E5,12) -> 42369 | G5: =EOMONTH(F5,12) -> 42735 | H5: =EOMONTH(G5,12) -> 43100
B6: Revenues | C6: 1500 | D6: 3500 | E6: 4500 | F6: =E6*(1+F21) -> 4500 | G6: =F6*(1+G21) -> 4500 | H6: =G6*(1+H21) -> 4500
B7: Cost of Goods Sold | C7: 1200 | D7: 3400 | E7: 4000 | F7: =F6*F22 -> 0 | G7: =G6*G22 -> 0 | H7: =H6*H22 -> 0
B8: Gross Profit | C8: =C6-C7 -> 300 | D8: =D6-D7 -> 100 | E8: =E6-E7 -> 500 | F8: =F6-F7 -> 4500 | G8: =G6-G7 -> 4500 | H8: =H6-H7 -> 4500
B9: Operating costs | C9: 55 | D9: 65 | E9: 78 | F9: 78 | G9: 78 | H9: 78
B10: Non-operating costs | C10: 15 | D10: 15 | E10: 15 | F10: 15 | G10: 15 | H10: 15
B11: Pretax Profit | C11: =C8-C9-C10 -> 230 | D11: =D8-D9-D10 -> 20 | E11: =E8-E9-E10 -> 407 | F11: =F8-F9-F10 -> 4407 | G11: =G8-G9-G10 -> 4407 | H11: =H8-H9-H10 -> 4407
B12: Taxes | C12: 80 | D12: 5 | E12: 141.6 | F12: =F11*F13 -> 1542.45 | G12: =G11*G13 -> 1542.45 | H12: =H11*H13 -> 1542.45
B13: Tax rate | C13: =C12/C11 -> 0.34782609 | D13: =D12/D11 -> 0.25 | E13: =E12/E11 -> 0.34791155 | F13: 0.35 | G13: 0.35 | H13: 0.35
B14: Net Profit | C14: =C11-C12 -> 150 | D14: =D11-D12 -> 15 | E14: =E11-E12 -> 265.4 | F14: =F11-F12 -> 2864.55 | G14: =G11-G12 -> 2864.55 | H14: =H11-H12 -> 2864.55
B15: Shares Outstanding | C15: 115 | D15: 120 | E15: 125 | F15: 125 | G15: 125 | H15: 125
B16: EPS | C16: =IF(C15,C14/C15,"NA") -> 1.3043478 | D16: =IF(D15,D14/D15,"NA") -> 0.125 | E16: =IF(E15,E14/E15,"NA") -> 2.1232 | F16: =IF(F15,F14/F15,"NA") -> 22.9164 | G16: =IF(G15,G14/G15,"NA") -> 22.9164 | H16: =IF(H15,H14/H15,"NA") -> 22.9164
B19: Select a case: | D19: <-insert a dropdown menu with the options Best case, Base case, Weak case
B21: Revenue growth (%) | I21: <-Using OFFSET & MATCH, output revenue growth based on the scenario selected in the dropdown
B22: COGS margin (%) | I22: <-Using OFFSET & MATCH, output COGS % margin based on the scenario selected in the dropdown
B24: Revenue
B25: Best case | F25: 0.24 | G25: =F25+0.02 -> 0.26 | H25: =G25+0.02 -> 0.28
B26: Base case | F26: 0.2 | G26: =F26+0.02 -> 0.22 | H26: =G26+0.02 -> 0.24
B27: Weak case | F27: 0.16 | G27: =F27+0.02 -> 0.18 | H27: =G27+0.02 -> 0.2
B29: COGS
B30: Best case | F30: 0.35 | G30: 0.4 | H30: 0.45
B31: Base case | F31: 0.4 | G31: 0.45 | H31: 0.5
B32: Weak case | F32: 0.45 | G32: 0.5 | H32: 0.55
E34: =F16 -> 22.9164
C35: Revenue growth rate assumptions: | D35: 0.16
D36: 0.18
D37: 0.2 | F37: <-Build a data table that outputs 2015 EPS at the revenue sensitivities above
D38: 0.22
D39: 0.24
E41: Revenue growth rate assumptions
E42: 0.16 | F42: 0.18 | G42: 0.2 | H42: 0.22 | I42: 0.24
D43: =F16 -> 22.9164 | J43: <-Build a data table that outputs 2015 EPS at the revenue sensitivities above
B45: Build a data table where the output is 2015 EPS, sensitized using BOTH the following inputs:
B46: Revenue growth rate assumptions | F46: 0.16 | G46: =F46+0.02 -> 0.18 | H46: 0.2 | I46: 0.22 | J46: 0.24
B47: Cost of Goods Sold margin assumptions | F47: 0.35 | G47: 0.37 | H47: 0.39 | I47: 0.41 | J47: 0.43 | K47: 0.45
D49: =F16 -> 22.9164 | E49: 0.16 | F49: =E49+0.02 -> 0.18 | G49: 0.2 | H49: 0.22 | I49: 0.24
D50: 0.39
D51: 0.38
D52: 0.37
D53: 0.36
D54: 0.35
D55: 0.34

Sheet Data table_ans
B1: Input Company Name: | C1: Lemonade Co.
B3: ="Income Statement for "&C1 -> Income Statement for Lemonade Co.
C4: Actuals | F4: Projections
C5: 41274 | D5: =EOMONTH(C5,12) -> 41639 | E5: =EOMONTH(D5,12) -> 42004 | F5: =EOMONTH(E5,12) -> 42369 | G5: =EOMONTH(F5,12) -> 42735 | H5: =EOMONTH(G5,12) -> 43100
B6: Revenues | C6: 1500 | D6: 3500 | E6: 4500 | F6: =E6*(1+F21) -> 5220 | G6: =F6*(1+G21) -> 6159.6 | H6: =G6*(1+H21) -> 7391.52
B7: Cost of Goods Sold | C7: 1200 | D7: 3400 | E7: 4000 | F7: =F6*F22 -> 2088 | G7: =G6*G22 -> 2771.82 | H7: =H6*H22 -> 3695.76
B8: Gross Profit | C8: =C6-C7 -> 300 | D8: =D6-D7 -> 100 | E8: =E6-E7 -> 500 | F8: =F6-F7 -> 3132 | G8: =G6-G7 -> 3387.78 | H8: =H6-H7 -> 3695.76
B9: Operating costs | C9: 55 | D9: 65 | E9: 78 | F9: 78 | G9: 78 | H9: 78
B10: Non-operating costs | C10: 15 | D10: 15 | E10: 15 | F10: 15 | G10: 15 | H10: 15
B11: Pretax Profit | C11: =C8-C9-C10 -> 230 | D11: =D8-D9-D10 -> 20 | E11: =E8-E9-E10 -> 407 | F11: =F8-F9-F10 -> 3039 | G11: =G8-G9-G10 -> 3294.78 | H11: =H8-H9-H10 -> 3602.76
B12: Taxes | C12: 80 | D12: 5 | E12: 141.6 | F12: =F11*F13 -> 1063.65 | G12: =G11*G13 -> 1153.173 | H12: =H11*H13 -> 1260.966
B13: Tax rate | C13: =C12/C11 -> 0.34782609 | D13: =D12/D11 -> 0.25 | E13: =E12/E11 -> 0.34791155 | F13: 0.35 | G13: 0.35 | H13: 0.35
B14: Net Profit | C14: =C11-C12 -> 150 | D14: =D11-D12 -> 15 | E14: =E11-E12 -> 265.4 | F14: =F11-F12 -> 1975.35 | G14: =G11-G12 -> 2141.607 | H14: =H11-H12 -> 2341.794
B15: Shares Outstanding | C15: 115 | D15: 120 | E15: 125 | F15: 125 | G15: 125 | H15: 125
B16: EPS | C16: =IF(C15,C14/C15,"NA") -> 1.3043478 | D16: =IF(D15,D14/D15,"NA") -> 0.125 | E16: =IF(E15,E14/E15,"NA") -> 2.1232 | F16: =IF(F15,F14/F15,"NA") -> 15.8028 | G16: =IF(G15,G14/G15,"NA") -> 17.132856 | H16: =IF(H15,H14/H15,"NA") -> 18.734352
B19: Select a case: | C19: Base case | D19: <-insert a dropdown menu with the options Best case, Base case, Weak case
B21: Revenue growth (%) | F21: =OFFSET(F24,MATCH($C$19,$B$25:$B$27,0),0) -> 0.16 | G21: =OFFSET(G24,MATCH($C$19,$B$25:$B$27,0),0) -> 0.18 | H21: =OFFSET(H24,MATCH($C$19,$B$25:$B$27,0),0) -> 0.2 | I21: <-Using OFFSET & MATCH, output revenue growth based on the scenario selected in the dropdown
B22: COGS margin (%) | F22: =OFFSET(F29,MATCH($C$19,$B$30:$B$32,0),0) -> 0.4 | G22: =OFFSET(G29,MATCH($C$19,$B$30:$B$32,0),0) -> 0.45 | H22: =OFFSET(H29,MATCH($C$19,$B$30:$B$32,0),0) -> 0.5 | I22: <-Using OFFSET & MATCH, output COGS % margin based on the scenario selected in the dropdown
B24: Revenue
B25: Best case | F25: 0.24 | G25: =F25+0.02 -> 0.26 | H25: =G25+0.02 -> 0.28
B26: Base case | F26: 0.16 | G26: =F26+0.02 -> 0.18 | H26: =G26+0.02 -> 0.2
B27: Weak case | F27: 0.16 | G27: =F27+0.02 -> 0.18 | H27: =G27+0.02 -> 0.2
B29: COGS
B30: Best case | F30: 0.35 | G30: 0.4 | H30: 0.45
B31: Base case | F31: 0.4 | G31: 0.45 | H31: 0.5
B32: Weak case | F32: 0.45 | G32: 0.5 | H32: 0.55
E34: =F16 -> 15.8028
C35: Revenue growth rate assumptions: | D35: 0.16 | E35: 15.8028
D36: 0.18 | E36: 16.0836
D37: 0.2 | E37: 16.3644 | F37: <-Build a data table that outputs 2015 EPS at the revenue sensitivities above
D38: 0.22 | E38: 16.6452
D39: 0.24 | E39: 16.926
E41: Revenue growth rate assumptions
E42: 0.16 | F42: 0.18 | G42: 0.2 | H42: 0.22 | I42: 0.24
D43: =F16 -> 15.8028 | E43: 15.8028 | F43: 16.0836 | G43: 16.3644 | H43: 16.6452 | I43: 16.926 | J43: <-Build a data table that outputs 2015 EPS at the revenue sensitivities above
B45: Build a data table where the output is 2015 EPS, sensitized using BOTH the following inputs:
B46: Revenue growth rate assumptions | F46: 0.16 | G46: =F46+0.02 -> 0.18 | H46: 0.2 | I46: 0.22 | J46: 0.24
B47: Cost of Goods Sold margin assumptions | F47: 0.35 | G47: 0.37 | H47: 0.39 | I47: 0.41 | J47: 0.43 | K47: 0.45
D49: =F16 -> 15.8028 | E49: 0.16 | F49: =E49+0.02 -> 0.18 | G49: 0.2 | H49: 0.22 | I49: 0.24
D50: 0.39 | E50: 16.07424 | F50: 16.35972 | G50: 16.6452 | H50: 16.93068 | I50: 17.21616
D51: 0.38 | E51: 16.34568 | F51: 16.63584 | G51: 16.926 | H51: 17.21616 | I51: 17.50632
D52: 0.37 | E52: 16.61712 | F52: 16.91196 | G52: 17.2068 | H52: 17.50164 | I52: 17.79648
D53: 0.36 | E53: 16.88856 | F53: 17.18808 | G53: 17.4876 | H53: 17.78712 | I53: 18.08664
D54: 0.35 | E54: 17.16 | F54: 17.4642 | G54: 17.7684 | H54: 18.0726 | I54: 18.3768
D55: 0.34 | E55: 17.43144 | F55: 17.74032 | G55: 18.0492 | H55: 18.35808 | I55: 18.66696

Sheet Self Referencing IFs
C2: 2015 Revenue growth assumptions
B3: ='Data table_ans'!F16 -> 15.8028 | C3: 0.16 | D3: 0.18 | E3: 0.2 | F3: 0.22
A4: 2015 | B4: 0.44 | C4: =IF(AND(C$3='Data table_ans'!$F$21,'Self Referencing IFs'!$B4='Data table_ans'!$F$22),'Data table_ans'!$F$16,'Self Referencing IFs'!C4) -> 14.71704 | D4: =IF(AND(D$3='Data table_ans'!$F$21,'Self Referencing IFs'!$B4='Data table_ans'!$F$22),'Data table_ans'!$F$16,'Self Referencing IFs'!D4) -> 14.97912 | E4: =IF(AND(E$3='Data table_ans'!$F$21,'Self Referencing IFs'!$B4='Data table_ans'!$F$22),'Data table_ans'!$F$16,'Self Referencing IFs'!E4) -> 15.2412 | F4: =IF(AND(F$3='Data table_ans'!$F$21,'Self Referencing IFs'!$B4='Data table_ans'!$F$22),'Data table_ans'!$F$16,'Self Referencing IFs'!F4) -> 15.50328
A5: COGS | B5: 0.42 | C5: =IF(AND(C$3='Data table_ans'!$F$21,'Self Referencing IFs'!$B5='Data table_ans'!$F$22),'Data table_ans'!$F$16,'Self Referencing IFs'!C5) -> 15.25992 | D5: =IF(AND(D$3='Data table_ans'!$F$21,'Self Referencing IFs'!$B5='Data table_ans'!$F$22),'Data table_ans'!$F$16,'Self Referencing IFs'!D5) -> 15.53136 | E5: =IF(AND(E$3='Data table_ans'!$F$21,'Self Referencing IFs'!$B5='Data table_ans'!$F$22),'Data table_ans'!$F$16,'Self Referencing IFs'!E5) -> 15.8028 | F5: =IF(AND(F$3='Data table_ans'!$F$21,'Self Referencing IFs'!$B5='Data table_ans'!$F$22),'Data table_ans'!$F$16,'Self Referencing IFs'!F5) -> 16.07424
A6: margin | B6: 0.4 | C6: =IF(AND(C$3='Data table_ans'!$F$21,'Self Referencing IFs'!$B6='Data table_ans'!$F$22),'Data table_ans'!$F$16,'Self Referencing IFs'!C6) -> 15.8028 | D6: =IF(AND(D$3='Data table_ans'!$F$21,'Self Referencing IFs'!$B6='Data table_ans'!$F$22),'Data table_ans'!$F$16,'Self Referencing IFs'!D6) -> 16.0836 | E6: =IF(AND(E$3='Data table_ans'!$F$21,'Self Referencing IFs'!$B6='Data table_ans'!$F$22),'Data table_ans'!$F$16,'Self Referencing IFs'!E6) -> 16.3644 | F6: =IF(AND(F$3='Data table_ans'!$F$21,'Self Referencing IFs'!$B6='Data table_ans'!$F$22),'Data table_ans'!$F$16,'Self Referencing IFs'!F6) -> 16.6452
A7: assumptions | B7: 0.38 | C7: =IF(AND(C$3='Data table_ans'!$F$21,'Self Referencing IFs'!$B7='Data table_ans'!$F$22),'Data table_ans'!$F$16,'Self Referencing IFs'!C7) -> 16.34568 | D7: =IF(AND(D$3='Data table_ans'!$F$21,'Self Referencing IFs'!$B7='Data table_ans'!$F$22),'Data table_ans'!$F$16,'Self Referencing IFs'!D7) -> 16.63584 | E7: =IF(AND(E$3='Data table_ans'!$F$21,'Self Referencing IFs'!$B7='Data table_ans'!$F$22),'Data table_ans'!$F$16,'Self Referencing IFs'!E7) -> 16.926 | F7: =IF(AND(F$3='Data table_ans'!$F$21,'Self Referencing IFs'!$B7='Data table_ans'!$F$22),'Data table_ans'!$F$16,'Self Referencing IFs'!F7) -> 17.21616

Sheet Math
B4: 2014 M&A League Tables | J4: Used for data validation:
B5: Advisors | C5: Geography | D5: # of deals | E5: Avg. deal size ($ in mm) | J5: US
B6: Libman Partners | C6: US | D6: 3 | E6: 1000 | J6: France
B7: Feldman Brothers | C7: US | D7: 4 | E7: 1200 | J7: Germany
B8: Barlow Associates | C8: Germany | D8: 7 | E8: 900
B9: McGowan & Company | C9: France | D9: 4 | E9: 800 | J9: Libman Partners
B10: Schmidt Capital | C10: US | D10: 8 | E10: 700 | J10: Feldman Brothers
B11: Chowdhry Management | C11: France | D11: 5 | E11: 600 | J11: Barlow Associates
B12: Feldman Brothers | C12: France | D12: 2 | E12: 500 | J12: McGowan & Company
B13: McGowan & Company | C13: US | D13: 1 | E13: 300 | J13: Schmidt Capital
B14: Chowdhry Management | C14: Germany | D14: 1 | E14: 200 | J14: Chowdhry Management
B15: Barlow Associates | C15: France | D15: 2 | E15: 700
B17: Select a region | K17: options | L17: exercise | M17: max proceeds
B18: Select an advisor: | J18: Tranche 1 | K18: 100 | L18: 10 | M18: =K18*L18 -> 1000
J19: Tranche 2 | K19: 200 | L19: 50 | M19: =K19*L19 -> 10000
B20: SUMPRODUCT | J20: Tranche 3 | K20: 300 | L20: 60 | M20: =K20*L20 -> 18000
B21: Calculate global M&A deal volume using SUMPRODUCT:
J22: strike | M22: 50
B23: Embedding criteria into SUMPRODUCT | J23: proceeds from in the $ options | M23: =SUMPRODUCT(K18:K20,L18:L20*(L18:L20<M22)) -> 1000
B24: Identify avg. deal size for the user-selected advisor AND region using SUMPRODUCT:
B25: Identify total deal volume for the user-selected advisor AND region using SUMPRODUCT: | J25: Turning TRUEs into 1s and FALSEs into 0s in Excel
J26: Number 1 | K26: 600
B27: SUMIF & AVERAGEIF | J27: Number 2 | K27: 500
B28: Calculate total number of deals done in the user-selected region using SUMIF: | J28: Number 1 is greater than Number 2 | K28: =K26>K27 -> TRUE | M28: <-Not recognized as 1
B29: Calculate the average number of deals done in the user-selected region using AVERAGEIF: | J29: Multiply this result by 1 | K29: =K28*1 -> 1 | M29: <-Recognized as 1
J30: Multiply this result by TRUE | K30: =K28*TRUE -> 1 | M30: <-Recognized as 1
B31: SUMIFS
B32: Identify avg. deal size for the user-selected advisor AND region using SUMIFS: | J32: Number 1 | K32: 200
B33: Identify total deal volume for the user-selected advisor AND region using SUMIFS | J33: Number 2 | K33: 500
J34: Number 1 is greater than Number 2 | K34: =K32>K33 -> FALSE | M34: <-Not recognized as 0
J35: Multiply this result by 1 | K35: =K34*1 -> 0 | M35: <-Recognized as 0
J36: Multiply this result by TRUE | K36: =K34*TRUE -> 0 | M36: <-Recognized as 0
J38: You MUST apply an operator to the TRUE or FALSE to make Excel recognize it as a 1 or 0

Sheet Math_ans
B4: 2014 M&A League Tables | J4: Used for data validation:
B5: Advisors | C5: Geography | D5: # of deals | E5: Avg. deal size ($ in mm) | J5: US
B6: Libman Partners | C6: US | D6: 3 | E6: 1000 | J6: France
B7: Feldman Brothers | C7: US | D7: 4 | E7: 1200 | J7: Germany
B8: Barlow Associates | C8: Germany | D8: 7 | E8: 900
B9: McGowan & Company | C9: France | D9: 4 | E9: 800 | J9: Libman Partners
B10: Schmidt Capital | C10: US | D10: 8 | E10: 700 | J10: Feldman Brothers
B11: Chowdhry Management | C11: France | D11: 5 | E11: 600 | J11: Barlow Associates
B12: Feldman Brothers | C12: France | D12: 2 | E12: 500 | J12: McGowan & Company
B13: McGowan & Company | C13: US | D13: 1 | E13: 300 | J13: Schmidt Capital
B14: Chowdhry Management | C14: Germany | D14: 1 | E14: 200 | J14: Chowdhry Management
B15: Barlow Associates | C15: France | D15: 2 | E15: 700
B17: Select a region | C17: France | K17: options | L17: exercise | M17: max proceeds
B18: Select an advisor: | C18: Feldman Brothers | J18: Tranche 1 | K18: 100 | L18: 10 | M18: =K18*L18 -> 1000
J19: Tranche 2 | K19: 200 | L19: 50 | M19: =K19*L19 -> 10000
B20: SUMPRODUCT | J20: Tranche 3 | K20: 300 | L20: 60 | M20: =K20*L20 -> 18000
B21: Calculate global M&A deal volume using SUMPRODUCT: | C21: =SUMPRODUCT(D6:D15,E6:E15) -> 28800
J22: strike | M22: 50
B23: Embedding criteria into SUMPRODUCT | J23: proceeds from in the $ options | M23: =SUMPRODUCT(K18:K20,L18:L20*(L18:L20<M22)) -> 1000
B24: Identify avg. deal size for the user-selected advisor AND region using SUMPRODUCT: | C24: =SUMPRODUCT((B6:B15=C18)*(C6:C15=C17),E6:E15) -> 500
B25: Identify total deal volume for the user-selected advisor AND region using SUMPRODUCT: | C25: =SUMPRODUCT((B6:B15=C18)*(C6:C15=C17),E6:E15,D6:D15) -> 1000 | J25: Turning TRUEs into 1s and FALSEs into 0s in Excel
J26: Number 1 | K26: 600
B27: SUMIF & AVERAGEIF | J27: Number 2 | K27: 500
B28: Calculate total number of deals done in the user-selected region using SUMIF: | C28: =SUMIF(C6:C15,C17,D6:D15) -> 13 | J28: Number 1 is greater than Number 2 | K28: =K26>K27 -> TRUE | M28: <-Not recognized as 1
B29: Calculate the average number of deals done in the user-selected region using AVERAGEIF: | C29: =AVERAGEIF(C6:C15,C17,D6:D15) -> 3.25 | J29: Multiply this result by 1 | K29: =K28*1 -> 1 | M29: <-Recognized as 1
J30: Multiply this result by TRUE | K30: =K28*TRUE -> 1 | M30: <-Recognized as 1
B31: SUMIFS
B32: Identify avg. deal size for the user-selected advisor AND region using SUMIFS: | C32: =SUMIFS(E6:E15,C6:C15,C17,B6:B15,C18) -> 500 | J32: Number 1 | K32: 200
B33: Identify total deal volume for the user-selected advisor AND region using SUMIFS | C33: =SUMIFS(E6:E15,C6:C15,C17,B6:B15,C18)*SUMIFS(D6:D15,C6:C15,C17,B6:B15,C18) -> 1000 | J33: Number 2 | K33: 500
J34: Number 1 is greater than Number 2 | K34: =K32>K33 -> FALSE | M34: <-Not recognized as 0
J35: Multiply this result by 1 | K35: =K34*1 -> 0 | M35: <-Recognized as 0
J36: Multiply this result by TRUE | K36: =K34*TRUE -> 0 | M36: <-Recognized as 0
J38: You MUST apply an operator to the TRUE or FALSE to make Excel recognize it as a 1 or 0

Sheet Other Useful Functions
A1: Absolute Value
B3: Input a number: | C3: -4
B4: Return absolute value | C4: =ABS(C3) -> 4 | D4: =ABS(C3)
A6: Ceiling
B8: Input EPS ($xx.xx): | C8: 4.23
B9: Round input up to nearest $0.05 | C9: =CEILING(C8,0.1) -> 4.3 | D9: =CEILING(C8,0.1)
A11: Floor
B13: Input EPS ($xx.xx): | C13: 4.23
B14: Round input down to nearest $0.05 | C14: =FLOOR(C13,0.05) -> 4.2 | D14: =FLOOR(C13,0.05)
A16: Combinations
B18: Input useful life (n years) of a fixed asset: | C18: 15
B19: Return sum of years' digits n(n+1)/2 | C19: =COMBIN(C18+1,2) -> 120 | D19: =COMBIN(C18+1,2)
A21: Round
B23: Net profits | C23: 1807
B24: Shares outstanding | C24: 123
B25: EPS | C25: =ROUND(C23/C24,2) -> 14.69 | D25: =ROUND(C23/C24,2)
A27: Round Up
B29: Net profits | C29: 1807
B30: Shares outstanding | C30: 123
B31: EPS | C31: =ROUNDUP(C29/C30,2) -> 14.7 | D31: =ROUNDUP(C23/C24,2)
A33: Round Down
B35: Net profits | C35: 1807
B36: Shares outstanding | C36: 123
B37: EPS | C37: =ROUNDDOWN(C35/C36,2) -> 14.69 | D37: =ROUNDDOWN(C23/C24,2)
A39: Max
C40: 2014 | D40: =C40+1 -> 2015 | E40: =D40+1 -> 2016 | F40: =E40+1 -> 2017
B41: Cash available to paydown / (needed from additional) short-term debt | C41: -200 | D41: 900 | E41: 750 | F41: 1040
B42: Short-term debt - Beginning of period | C42: 800 | D42: =C43 -> 0 | E42: =D43 -> 0 | F42: =E43 -> 0
B43: Short-term debt - End of period (using MAX)
A45: Min
B46: Borrowing capacity will be calculated as 5x (the lesser of last year's EBITDA or the average EBITDA over the last three years)
C48: 2014 | D48: =C48+1 -> 2015 | E48: =D48+1 -> 2016 | F48: Average
B49: EBITDA | C49: 350 | D49: =C49*1.05 -> 367.5 | E49: =D49*1.05 -> 385.875 | F49: =AVERAGE(C49:E49) -> 367.79167
B50: Borrowing capacity
A52: Count
B53: Property | C53: Price (000's)
B54: Hillside | C54: 348
B55: Riviera | C55: 263
B56: Agora | C56: Sold
B57: Lexington | C57: 309
B58: Tremont | C58: 123
B59: Weymouth | C59: Sold
B60: York | C60: 131
B61: Deville | C61: 238
B62: Cobble Hill | C62: 385
B64: Number of Properties Available for Sale | D64: =COUNT(C54:C62)
B65: Number of Properties Available for Sale or Sold | D65: =COUNTA(C54:C62)
B66: Number of Properties > $250,000 | D66: =COUNTIF(C54:C62,">250")
A68: Product
B70: 2011 Free Cash Flow | C70: 1500
B71: Weighted Average Cost of Capital (WACC) | C71: 0.08
B72: Discount Factor | C72: =1/(1+C71)^2 -> 0.85733882
B73: Midyear Adjustment Factor | C73: =(1+C71)^0.5 -> 1.0392305
B74: Present Value Cash Flow (2009)
A76: PV and FV
C77: PV | E77: FV
B78: Annual interest rate | C78: 0.12 | E78: 0.12
B79: Payment amount per month | C79: -500 | E79: -500
B80: Life of loan | C80: 5 | E80: 5
B81: Payment made at the beginning of each period | C81: 1 | E81: 1
B82: Rate per month | C82: =C78/12 -> 0.01 | E82: =E78/12 -> 0.01
B83: Number of payments | C83: =C80*12 -> 60 | E83: =E80*12 -> 60
A86: NPV
C87: NPV
B88: Annual discount rate | C88: 0.12
B89: Cash outflow on 12/31/14 | C89: -1000
B90: Cash inflow on 12/31/15 | C90: 250
B91: Cash inflow on 12/31/16 | C91: 400
B92: Cash inflow on 12/31/17 | C92: 500
B93: Cash inflow on 12/31/18 | C93: 480
B94: Cash inflow on 12/31/19 | C94: 700
F96: NPV vs XNPV
A97: XNPV | K97: Hacking NPV to calculate off BOP
C98: XNPV | G98: NPV | I98: XNPV | K98: NPV
B99: Annual discount rate | C99: 0.12 | F99: rate: | G99: 0.1 | H99: rate: | I99: 0.1 | J99: rate: | K99: 0.1
B100: 41741 | C100: -1000 | F100: 42004 | G100: 1000 | I100: 1000 | K100: 1000
B101: 42035 | C101: 250 | F101: =EOMONTH(F100,12) -> 42369 | G101: 1000 | I101: 1000 | K101: 1000
B102: 42277 | C102: 400 | F102: =EOMONTH(F101,12) -> 42735 | G102: 1000 | I102: 1000 | K102: 1000
B103: 42551 | C103: 500 | F103: =EOMONTH(F102,12) -> 43100 | G103: 1000 | I103: 1000 | K103: 1000
B104: 43220 | C104: 480 | G104: =NPV(G99,G100:G103) -> 3169.8654 | I104: =XNPV(I99,I100:I103,F100:F103) -> 3486.4401 | K104: =K100+NPV(K99,K101:K103) -> 3486.852
B105: 43251 | C105: 700 | G105: =NPV(G99,G100:G103) | I105: =XNPV(I99,I100:I103,F100:F103)
A108: IRR | F108: IRR vs XIRR
B109: Initial investment expenditure | C109: -1000
B110: ="Cash inflow after period " & 1 -> Cash inflow after period 1 | C110: 100 | G110: IRR | I110: XIRR
B111: ="Cash inflow after period " & 2 -> Cash inflow after period 2 | C111: 200 | F111: 41741 | G111: -1000 | I111: -1000
B112: ="Cash inflow after period " & 3 -> Cash inflow after period 3 | C112: 300 | F112: 42035 | G112: 400 | I112: 400
B113: ="Cash inflow after period " & 4 -> Cash inflow after period 4 | C113: 400 | F113: 42277 | G113: 300 | I113: 300
B114: ="Cash inflow after period " & 5 -> Cash inflow after period 5 | C114: 500 | F114: 42551 | G114: 800 | I114: 800
B115: Internal Rate of Return | G115: =IRR(G111:G114) -> 0.20260726 | I115: =XIRR(I111:I114,F111:F114) -> 0.27937058
G116: =IRR(G111:G114) | I116: =XIRR(I111:I114,F111:F114)
A117: XIRR
B119: Dates of Cash Flows | C119: Cash Flows
B120: 41741 | C120: -1000
B121: 42035 | C121: 100
B122: 42277 | C122: 200
B123: 42551 | C123: 300
B124: 43220 | C124: 400
B125: 43251 | C125: 500
B126: Internal Rate of Return
A128: Goal Seek
...

Sheet Other Useful Functions_ans
A1: Absolute Value
B3: Input a number: | C3: -4
B4: Return absolute value | C4: =ABS(C3) -> 4 | D4: =ABS(C3)
A6: Ceiling
B8: Input EPS ($xx.xx): | C8: 4.23
B9: Round input up to nearest $0.05 | C9: =CEILING(C8,0.1) -> 4.3 | D9: =CEILING(C8,0.1)
A11: Floor
B13: Input EPS ($xx.xx): | C13: 4.23
B14: Round input down to nearest $0.05 | C14: =FLOOR(C13,0.05) -> 4.2 | D14: =FLOOR(C13,0.05)
A16: Combinations
B18: Input useful life (n years) of a fixed asset: | C18: 15
B19: Return sum of years' digits n(n+1)/2 | C19: =COMBIN(C18+1,2) -> 120 | D19: =COMBIN(C18+1,2)
A21: Round
B23: Net profits | C23: 1807
B24: Shares outstanding | C24: 123
B25: EPS | C25: =ROUND(C23/C24,2) -> 14.69 | D25: =ROUND(C23/C24,2)
A27: Round Up
B29: Net profits | C29: 1807
B30: Shares outstanding | C30: 123
B31: EPS | C31: =ROUNDUP(C29/C30,2) -> 14.7 | D31: =ROUNDUP(C23/C24,2)
A33: Round Down
B35: Net profits | C35: 1807
B36: Shares outstanding | C36: 123
B37: EPS | C37: =ROUNDDOWN(C35/C36,2) -> 14.69 | D37: =ROUNDDOWN(C23/C24,2)
A39: Max
C40: 2014 | D40: =C40+1 -> 2015 | E40: =D40+1 -> 2016 | F40: =E40+1 -> 2017
B41: Cash available to paydown / (needed from additional) short-term debt | C41: -200 | D41: 900 | E41: 750 | F41: 1040
B42: Short-term debt - Beginning of period | C42: 800 | D42: =C43 -> 1000 | E42: =D43 -> 100 | F42: =E43 -> 0
B43: Short-term debt - End of period (using MAX) | C43: =MAX(0,C42-C41) -> 1000 | D43: =MAX(0,D42-D41) -> 100 | E43: =MAX(0,E42-E41) -> 0 | F43: =MAX(0,F42-F41) -> 0
C44: =MAX(0,C42-C41)
A45: Min
B46: Borrowing capacity will be calculated as 5 x (the lesser of last year's EBITDA or the average EBITDA over the last three years)
C48: 2014 | D48: =C48+1 -> 2015 | E48: =D48+1 -> 2016 | F48: Average
B49: EBITDA | C49: 350 | D49: =C49*1.05 -> 367.5 | E49: =D49*1.05 -> 385.875 | F49: =AVERAGE(C49:E49) -> 367.79167
B50: Borrowing capacity | C50: =5*MIN(F49,E49) -> 1838.9583 | D50: =5*MIN(F49,E49)
A52: Count
B53: Property | C53: Price (000's)
B54: Hillside | C54: 348
B55: Riviera | C55: 263
B56: Agora | C56: Sold
B57: Lexington | C57: 309
B58: Tremont | C58: 123
B59: Weymouth | C59: Sold
B60: York | C60: 131
B61: Deville | C61: 238
B62: Cobble Hill | C62: 385
B64: Number of Properties Available for Sale | C64: =COUNT(C54:C62) -> 7 | D64: =COUNT(C54:C62)
B65: Number of Properties Available for Sale or Sold | C65: =COUNTA(C54:C62) -> 9 | D65: =COUNTA(C54:C62)
B66: Number of Properties > $250,000 | C66: =COUNTIF(C54:C62,">250") -> 4 | D66: =COUNTIF(C54:C62,">250")
A68: Product
B70: 2011 Free Cash Flow | C70: 1500
B71: Weighted Average Cost of Capital (WACC) | C71: 0.08
B72: Discount Factor | C72: =1/(1+C71)^2 -> 0.85733882
B73: Midyear Adjustment Factor | C73: =(1+C71)^0.5 -> 1.0392305
B74: Present Value Cash Flow (2009) | C74: =PRODUCT(C70,C72,C73) -> 1336.459 | D74: =PRODUCT(C81,C83,C84)
A76: PV and FV
C77: PV | E77: FV
B78: Annual interest rate | C78: 0.12 | E78: 0.12
B79: Payment amount per month | C79: -500 | E79: -500
B80: Life of loan | C80: 5 | E80: 5
B81: Payment made at the beginning of each period | C81: 1 | E81: 1
B82: Rate per month | C82: =C78/12 -> 0.01 | E82: =E78/12 -> 0.01
B83: Number of payments | C83: =C80*12 -> 60 | E83: =E80*12 -> 60
C84: =PV(C82,C83,C79,,C81) -> 22702.294 | E84: =FV(E82,E83,E79,,E81) -> 41243.183
A86: NPV
C87: NPV
B88: Annual discount rate | C88: 0.12
B89: Cash outflow on 12/31/14 | C89: -1000
B90: Cash inflow on 12/31/15 | C90: 250
B91: Cash inflow on 12/31/16 | C91: 400
B92: Cash inflow on 12/31/17 | C92: 500
B93: Cash inflow on 12/31/18 | C93: 480
B94: Cash inflow on 12/31/19 | C94: 700
C95: =NPV(C88,C89:C94) -> 535.91914
F96: NPV vs XNPV
A97: XNPV | K97: Hacking NPV to calculate off BOP
C98: XNPV | G98: NPV | I98: XNPV | K98: NPV
B99: Annual discount rate | C99: 0.12 | F99: rate: | G99: 0.1 | H99: rate: | I99: 0.1 | J99: rate: | K99: 0.1
B100: 41741 | C100: -1000 | F100: 42004 | G100: 1000 | I100: 1000 | K100: 1000
B101: 42035 | C101: 250 | F101: =EOMONTH(F100,12) -> 42369 | G101: 1000 | I101: 1000 | K101: 1000
B102: 42277 | C102: 400 | F102: =EOMONTH(F101,12) -> 42735 | G102: 1000 | I102: 1000 | K102: 1000
B103: 42551 | C103: 500 | F103: =EOMONTH(F102,12) -> 43100 | G103: 1000 | I103: 1000 | K103: 1000
B104: 43220 | C104: 480 | G104: =NPV(G99,G100:G103) -> 3169.8654 | I104: =XNPV(I99,I100:I103,F100:F103) -> 3486.4401 | K104: =K100+NPV(K99,K101:K103) -> 3486.852
B105: 43251 | C105: 700 | G105: =NPV(G99,G100:G103) | I105: =XNPV(I99,I100:I103,F100:F103)
C106: =XNPV(C99,C100:C105,B100:B105) -> 696.94724
A108: IRR | F108: IRR vs XIRR
B109: Initial investment expenditure | C109: -1000
B110: ="Cash inflow after period " & 1 -> Cash inflow after period 1 | C110: 100 | G110: IRR | I110: XIRR
B111: ="Cash inflow after period " & 2 -> Cash inflow after period 2 | C111: 200 | F111: 41741 | G111: -1000 | I111: -1000
B112: ="Cash inflow after period " & 3 -> Cash inflow after period 3 | C112: 300 | F112: 42035 | G112: 400 | I112: 400
B113: ="Cash inflow after period " & 4 -> Cash inflow after period 4 | C113: 400 | F113: 42277 | G113: 300 | I113: 300
B114: ="Cash inflow after period " & 5 -> Cash inflow after period 5 | C114: 500 | F114: 42551 | G114: 800 | I114: 800
B115: Internal Rate of Return | C115: =IRR(C109:C114) -> 0.12005762 | G115: =IRR(G111:G114) -> 0.20260726 | I115: =XIRR(I111:I114,F111:F114) -> 0.27937058
G116: =IRR(G111:G114) | I116: =XIRR(I111:I114,F111:F114)
A117: XIRR
B119: Dates of Cash Flows | C119: Cash Flows
B120: 41741 | C120: -1000
B121: 42035 | C121: 100
B122: 42277 | C122: 200
B123: 42551 | C123: 300
...

Sheet COUNT & COUNTIF
B2: Car Sales by Manufacturer, Region, and Date
B5: Sale date | C5: Manufacturer | D5: MSRP | E5: Region | G5: USING COUNTIFS
B6: 41570 | C6: GM | D6: 11197 | E6: USA | G6: Total transactions
B7: 41386 | C7: Fiat | D7: 20335 | E7: Canada | G7: Total transactions less than | H7: 20000
B8: 41711 | C8: Toyota | D8: 20874 | E8: USA | G8: Total transactions between | H8: 20000 | I8: 30000
B9: 41774 | C9: GM | D9: 20166 | E9: Latin America | G9: Total transactions greater than | H9: 30000
B10: 41912 | C10: Ford | D10: 26349 | E10: USA
B11: 41228 | C11: Ford | D11: 17918 | E11: Latin America
B12: 41503 | C12: Toyota | D12: 39341 | E12: Latin America
B13: 41619 | C13: GM | D13: 33241 | E13: USA
B14: 41515 | C14: Fiat | D14: 22824 | E14: Latin America
B15: 41752 | C15: Toyota | D15: 15745 | E15: Mexico
B16: 41257 | C16: Ford | D16: 22782 | E16: Mexico
B17: 41158 | C17: Toyota | D17: 14181 | E17: USA
B18: 41701 | C18: GM | D18: 28985 | E18: USA
B19: 41930 | C19: Fiat | D19: 6242 | E19: Mexico
B20: 41507 | C20: Toyota | D20: 19720 | E20: Mexico
B21: 41793 | C21: Toyota | D21: 30713 | E21: Latin America
... B1156: 41343 | C1156: Toyota | D1156: 25329 | E1156: USA

Sheet COUNT & COUNTIF_ans
B2: Car Sales by Manufacturer, Region, and Date
B5: Sale date | C5: Manufacturer | D5: MSRP | E5: Region | G5: USING COUNTIFS
B6: 41570 | C6: GM | D6: 11197 | E6: USA | G6: Total transactions | J6: =COUNT(D6:D1156) -> 1151
B7: 41386 | C7: Fiat | D7: 20335 | E7: Canada | G7: Total transactions less than | H7: 20000 | J7: =COUNTIF(D6:D1156,"<"&H7) -> 498
B8: 41711 | C8: Toyota | D8: 20874 | E8: USA | G8: Total transactions between | H8: 20000 | I8: 30000 | J8: =COUNTIFS(D6:D1156,">"&H8,D6:D1156,"<"&I8) -> 331
B9: 41774 | C9: GM | D9: 20166 | E9: Latin America | G9: Total transactions greater than | H9: 30000 | J9: =COUNTIF(D6:D1156,">="&H9) -> 322
B10: 41912 | C10: Ford | D10: 26349 | E10: USA
B11: 41228 | C11: Ford | D11: 17918 | E11: Latin America
B12: 41503 | C12: Toyota | D12: 39341 | E12: Latin America
B13: 41619 | C13: GM | D13: 33241 | E13: USA
B14: 41515 | C14: Fiat | D14: 22824 | E14: Latin America
B15: 41752 | C15: Toyota | D15: 15745 | E15: Mexico
B16: 41257 | C16: Ford | D16: 22782 | E16: Mexico
B17: 41158 | C17: Toyota | D17: 14181 | E17: USA
B18: 41701 | C18: GM | D18: 28985 | E18: USA
B19: 41930 | C19: Fiat | D19: 6242 | E19: Mexico
B20: 41507 | C20: Toyota | D20: 19720 | E20: Mexico
B21: 41793 | C21: Toyota | D21: 30713 | E21: Latin America
... B1156: 41343 | C1156: Toyota | D1156: 25329 | E1156: USA

Sheet Sheet5
T2: Critera Q1 | U2: Criteria Q2 | V2: Criteria Q3
B3: COUNTIF Criteria | D3: Range 1 | E3: Criteria | T3: United States | U3: United States | V3: United States
B4: The criteria in count is mostly used to test weather the array is <> or = to a | D4: 23 | E4: 23 | U4: Germany | V4: Germany
B5: specific criteria or another range (doesn't have to be the same length). | D5: 23 | J5: List of countries | L5: Olympic event | M5: Gold | N5: Silver | O5: Bronze | P5: Q1 | Q5: Q2 | R5: Q3 | U5: France | V5: France
B6: For example, given the critera and range, countif will tell us | D6: 14 | J6: Andorra | L6: 1 | M6: United Kingdom | N6: Germany | O6: France | P6: =MIN(1,COUNTIF(M6:O6,$T$3)) -> 0 | Q6: =MIN(1,(COUNTIF(M6:O6,$U$3)+COUNTIF(M6:O6,$U$4)+COUNTIF(M6:O6,$U$5))) -> 1 | R6: =SUMPRODUCT(COUNTIF(M6:O6,$V$3:$V$5)) -> 2
B7: How many #s in range equal the number in the criteria (23): | D7: =COUNTIF(D4:D6,E4) -> 2 | E7: <-=COUNTIF(D4:D6,E4) is the "long form" syntax for equal | J7: United Arab Emirates | L7: =L6+1 -> 2 | M7: China | N7: Colombia | O7: China | P7: =MIN(1,COUNTIF(M7:O7,$T$3)) -> 0 | Q7: =MIN(1,(COUNTIF(M7:O7,$U$3)+COUNTIF(M7:O7,$U$4)+COUNTIF(M7:O7,$U$5))) -> 0 | R7: =SUMPRODUCT(COUNTIF(M7:O7,$V$3:$V$5)) -> 0 | T7: Question 1: | U7: In how many events did the United States earn a medal? | AA7: =SUM(P6:P101) -> 10
B8: How many # greater than 23: | D8: =COUNTIF(D4:D6,">"&E4) -> 0 | J8: Afghanistan | L8: =L7+1 -> 3 | M8: Cuba | N8: Ukraine | O8: Poland | P8: =MIN(1,COUNTIF(M8:O8,$T$3)) -> 0 | Q8: =MIN(1,(COUNTIF(M8:O8,$U$3)+COUNTIF(M8:O8,$U$4)+COUNTIF(M8:O8,$U$5))) -> 0 | R8: =SUMPRODUCT(COUNTIF(M8:O8,$V$3:$V$5)) -> 0 | T8: Question 2: | U8: In how many events did either the US, Germany or France win a medal? | AA8: =SUM(Q6:Q101) -> 15
B9: How many # less than 23: | D9: =COUNTIF(D4:D6,"<"&E4) -> 1 | J9: Antigua and Barbuda | L9: =L8+1 -> 4 | M9: Colombia | N9: Colombia | O9: Russia | P9: =MIN(1,COUNTIF(M9:O9,$T$3)) -> 0 | Q9: =MIN(1,(COUNTIF(M9:O9,$U$3)+COUNTIF(M9:O9,$U$4)+COUNTIF(M9:O9,$U$5))) -> 0 | R9: =SUMPRODUCT(COUNTIF(M9:O9,$V$3:$V$5)) -> 0 | T9: Question 3: | U9: How many total medals were won by US, Germany and France? | AA9: =SUM(R6:R101) -> 18
B10: How many # less than or equal to 23: | D10: =COUNTIF(D4:D6,"<="&E4) -> 3 | J10: Anguilla | L10: =L9+1 -> 5 | M10: Portugal | N10: United States | O10: Indonesia | P10: =MIN(1,COUNTIF(M10:O10,$T$3)) -> 1 | Q10: =MIN(1,(COUNTIF(M10:O10,$U$3)+COUNTIF(M10:O10,$U$4)+COUNTIF(M10:O10,$U$5))) -> 1 | R10: =SUMPRODUCT(COUNTIF(M10:O10,$V$3:$V$5)) -> 1
B11: Crtiera can be both numbers or text. | J11: Albania | L11: =L10+1 -> 6 | M11: United States | N11: China | O11: Peru | P11: =MIN(1,COUNTIF(M11:O11,$T$3)) -> 1 | Q11: =MIN(1,(COUNTIF(M11:O11,$U$3)+COUNTIF(M11:O11,$U$4)+COUNTIF(M11:O11,$U$5))) -> 1 | R11: =SUMPRODUCT(COUNTIF(M11:O11,$V$3:$V$5)) -> 1 | T11: Bonus: Using wildcards
J12: Argentina | L12: =L11+1 -> 7 | M12: Indonesia | N12: Vietnam | O12: Croatia | P12: =MIN(1,COUNTIF(M12:O12,$T$3)) -> 0 | Q12: =MIN(1,(COUNTIF(M12:O12,$U$3)+COUNTIF(M12:O12,$U$4)+COUNTIF(M12:O12,$U$5))) -> 0 | R12: =SUMPRODUCT(COUNTIF(M12:O12,$V$3:$V$5)) -> 0 | T12: How many countries contain the word "united" in their name ? | AA12: =COUNTIF(J6:J246,"*united*") -> 3
B13: The criteria in count doesn’t have to be one data point - it can be an array. | D13: Range 1 | E13: Crtiera range | J13: American Samoa | L13: =L12+1 -> 8 | M13: Philippines | N13: Tunisia | O13: Indonesia | P13: =MIN(1,COUNTIF(M13:O13,$T$3)) -> 0 | Q13: =MIN(1,(COUNTIF(M13:O13,$U$3)+COUNTIF(M13:O13,$U$4)+COUNTIF(M13:O13,$U$5))) -> 0 | R13: =SUMPRODUCT(COUNTIF(M13:O13,$V$3:$V$5)) -> 0 | T13: How many countries start with the letter "A"? | AA13: =COUNTIF(J7:J247,"A*") -> 11
B14: For example, in this example, the countif function is storing how many times | D14: 23 | E14: 2 | J14: Austria | L14: =L13+1 -> 9 | M14: United States | N14: China | O14: Comoros | P14: =MIN(1,COUNTIF(M14:O14,$T$3)) -> 1 | Q14: =MIN(1,(COUNTIF(M14:O14,$U$3)+COUNTIF(M14:O14,$U$4)+COUNTIF(M14:O14,$U$5))) -> 1 | R14: =SUMPRODUCT(COUNTIF(M14:O14,$V$3:$V$5)) -> 1
B15: the criteria range contained the same numbers as in the range: | D15: 12 | E15: 7 | J15: Australia | L15: =L14+1 -> 10 | M15: Russia | N15: United States | O15: Poland | P15: =MIN(1,COUNTIF(M15:O15,$T$3)) -> 1 | Q15: =MIN(1,(COUNTIF(M15:O15,$U$3)+COUNTIF(M15:O15,$U$4)+COUNTIF(M15:O15,$U$5))) -> 1 | R15: =SUMPRODUCT(COUNTIF(M15:O15,$V$3:$V$5)) -> 1
D16: 14 | E16: 23 | J16: Aruba | L16: =L15+1 -> 11 | M16: Poland | N16: China | O16: Philippines | P16: =MIN(1,COUNTIF(M16:O16,$T$3)) -> 0 | Q16: =MIN(1,(COUNTIF(M16:O16,$U$3)+COUNTIF(M16:O16,$U$4)+COUNTIF(M16:O16,$U$5))) -> 0 | R16: =SUMPRODUCT(COUNTIF(M16:O16,$V$3:$V$5)) -> 0
B17: But note that it doesn't sum the array. For that you need to wrap a | E17: 1 | J17: Azerbaijan | L17: =L16+1 -> 12 | M17: United States | N17: South Korea | O17: Brazil | P17: =MIN(1,COUNTIF(M17:O17,$T$3)) -> 1 | Q17: =MIN(1,(COUNTIF(M17:O17,$U$3)+COUNTIF(M17:O17,$U$4)+COUNTIF(M17:O17,$U$5))) -> 1 | R17: =SUMPRODUCT(COUNTIF(M17:O17,$V$3:$V$5)) -> 1
B18: SUMPRODUCT function around it (and you cant use SUM: | E18: 12 | J18: Bosnia and Herzegovina | L18: =L17+1 -> 13 | M18: Russia | N18: Colombia | O18: Germany | P18: =MIN(1,COUNTIF(M18:O18,$T$3)) -> 0 | Q18: =MIN(1,(COUNTIF(M18:O18,$U$3)+COUNTIF(M18:O18,$U$4)+COUNTIF(M18:O18,$U$5))) -> 1 | R18: =SUMPRODUCT(COUNTIF(M18:O18,$V$3:$V$5)) -> 1
B19: This works because SUMPRODCT instructs excel to sum all the arguments | D19: =COUNTIF(D14:D16,E14:E18) -> 0 | E19: This formula, while outputting 0 - actually stores the array {0;0;1;0;1} | J19: Barbados | L19: =L18+1 -> 14 | M19: Indonesia | N19: China | O19: Venezuela | P19: =MIN(1,COUNTIF(M19:O19,$T$3)) -> 0 | Q19: =MIN(1,(COUNTIF(M19:O19,$U$3)+COUNTIF(M19:O19,$U$4)+COUNTIF(M19:O19,$U$5))) -> 0 | R19: =SUMPRODUCT(COUNTIF(M19:O19,$V$3:$V$5)) -> 0
B20: in the array. If there's a second array (i.e. the traditional use of sumproduct) | D20: =SUMPRODUCT(COUNTIF(D14:D16,E14:E18)) -> 2 | J20: Bangladesh | L20: =L19+1 -> 15 | M20: Portugal | N20: Philippines | O20: Indonesia | P20: =MIN(1,COUNTIF(M20:O20,$T$3)) -> 0 | Q20: =MIN(1,(COUNTIF(M20:O20,$U$3)+COUNTIF(M20:O20,$U$4)+COUNTIF(M20:O20,$U$5))) -> 0 | R20: =SUMPRODUCT(COUNTIF(M20:O20,$V$3:$V$5)) -> 0
B21: then it multiplies the first arguments of each array before summing. | J21: Belgium | L21: =L20+1 -> 16 | M21: Israel | N21: Ethiopia | O21: Libya | P21: =MIN(1,COUNTIF(M21:O21,$T$3)) -> 0 | Q21: =MIN(1,(COUNTIF(M21:O21,$U$3)+COUNTIF(M21:O21,$U$4)+COUNTIF(M21:O21,$U$5))) -> 0 | R21: =SUMPRODUCT(COUNTIF(M21:O21,$V$3:$V$5)) -> 0
B22: But if there isnt a second array, it just sums everything up, like SUM. But unlike | J22: Burkina Faso | L22: =L21+1 -> 17 | M22: Indonesia | N22: Kazakhstan | O22: Peru | P22: =MIN(1,COUNTIF(M22:O22,$T$3)) -> 0 | Q22: =MIN(1,(COUNTIF(M22:O22,$U$3)+COUNTIF(M22:O22,$U$4)+COUNTIF(M22:O22,$U$5))) -> 0 | R22: =SUMPRODUCT(COUNTIF(M22:O22,$V$3:$V$5)) -> 0
B23: SUM, you can feed an array to sumproduct | J23: Bulgaria | L23: =L22+1 -> 18 | M23: China | N23: Georgia | O23: El Salvador | P23: =MIN(1,COUNTIF(M23:O23,$T$3)) -> 0 | Q23: =MIN(1,(COUNTIF(M23:O23,$U$3)+COUNTIF(M23:O23,$U$4)+COUNTIF(M23:O23,$U$5))) -> 0 | R23: =SUMPRODUCT(COUNTIF(M23:O23,$V$3:$V$5)) -> 0
J24: Bahrain | L24: =L23+1 -> 19 | M24: Brazil | N24: Bulgaria | O24: United Kingdom | P24: =MIN(1,COUNTIF(M24:O24,$T$3)) -> 0 | Q24: =MIN(1,(COUNTIF(M24:O24,$U$3)+COUNTIF(M24:O24,$U$4)+COUNTIF(M24:O24,$U$5))) -> 0 | R24: =SUMPRODUCT(COUNTIF(M24:O24,$V$3:$V$5)) -> 0
J25: Burundi | L25: =L24+1 -> 20 | M25: Indonesia | N25: Morocco | O25: China | P25: =MIN(1,COUNTIF(M25:O25,$T$3)) -> 0 | Q25: =MIN(1,(COUNTIF(M25:O25,$U$3)+COUNTIF(M25:O25,$U$4)+COUNTIF(M25:O25,$U$5))) -> 0 | R25: =SUMPRODUCT(COUNTIF(M25:O25,$V$3:$V$5)) -> 0
J26: Benin | L26: =L25+1 -> 21 | M26: China | N26: Ukraine | O26: China | P26: =MIN(1,COUNTIF(M26:O26,$T$3)) -> 0 | Q26: =MIN(1,(COUNTIF(M26:O26,$U$3)+COUNTIF(M26:O26,$U$4)+COUNTIF(M26:O26,$U$5))) -> 0 | R26: =SUMPRODUCT(COUNTIF(M26:O26,$V$3:$V$5)) -> 0
J27: Bermuda | L27: =L26+1 -> 22 | M27: China | N27: China | O27: China | P27: =MIN(1,COUNTIF(M27:O27,$T$3)) -> 0 | Q27: =MIN(1,(COUNTIF(M27:O27,$U$3)+COUNTIF(M27:O27,$U$4)+COUNTIF(M27:O27,$U$5))) -> 0 | R27: =SUMPRODUCT(COUNTIF(M27:O27,$V$3:$V$5)) -> 0
J28: Brunei | L28: =L27+1 -> 23 | M28: United States | N28: China | O28: China | P28: =MIN(1,COUNTIF(M28:O28,$T$3)) -> 1 | Q28: =MIN(1,(COUNTIF(M28:O28,$U$3)+COUNTIF(M28:O28,$U$4)+COUNTIF(M28:O28,$U$5))) -> 1 | R28: =SUMPRODUCT(COUNTIF(M28:O28,$V$3:$V$5)) -> 1
J29: Bolivia | L29: =L28+1 -> 24 | M29: Indonesia | N29: China | O29: China | P29: =MIN(1,COUNTIF(M29:O29,$T$3)) -> 0 | Q29: =MIN(1,(COUNTIF(M29:O29,$U$3)+COUNTIF(M29:O29,$U$4)+COUNTIF(M29:O29,$U$5))) -> 0 | R29: =SUMPRODUCT(COUNTIF(M29:O29,$V$3:$V$5)) -> 0
J30: Brazil | L30: =L29+1 -> 25 | M30: Armenia | N30: France | O30: Colombia | P30: =MIN(1,COUNTIF(M30:O30,$T$3)) -> 0 | Q30: =MIN(1,(COUNTIF(M30:O30,$U$3)+COUNTIF(M30:O30,$U$4)+COUNTIF(M30:O30,$U$5))) -> 1 | R30: =SUMPRODUCT(COUNTIF(M30:O30,$V$3:$V$5)) -> 1
J31: Bahamas | L31: =L30+1 -> 26 | M31: Ukraine | N31: Peru | O31: Honduras | P31: =MIN(1,COUNTIF(M31:O31,$T$3)) -> 0 | Q31: =MIN(1,(COUNTIF(M31:O31,$U$3)+COUNTIF(M31:O31,$U$4)+COUNTIF(M31:O31,$U$5))) -> 0 | R31: =SUMPRODUCT(COUNTIF(M31:O31,$V$3:$V$5)) -> 0
J32: Bhutan | L32: =L31+1 -> 27 | M32: Sweden | N32: Sweden | O32: Philippines | P32: =MIN(1,COUNTIF(M32:O32,$T$3)) -> 0 | Q32: =MIN(1,(COUNTIF(M32:O32,$U$3)+COUNTIF(M32:O32,$U$4)+COUNTIF(M32:O32,$U$5))) -> 0 | R32: =SUMPRODUCT(COUNTIF(M32:O32,$V$3:$V$5)) -> 0
J33: Bouvet Island | L33: =L32+1 -> 28 | M33: Czech Republic | N33: Argentina | O33: Ukraine | P33: =MIN(1,COUNTIF(M33:O33,$T$3)) -> 0 | Q33: =MIN(1,(COUNTIF(M33:O33,$U$3)+COUNTIF(M33:O33,$U$4)+COUNTIF(M33:O33,$U$5))) -> 0 | R33: =SUMPRODUCT(COUNTIF(M33:O33,$V$3:$V$5)) -> 0
J34: Botswana | L34: =L33+1 -> 29 | M34: Russia | N34: China | O34: Malaysia | P34: =MIN(1,COUNTIF(M34:O34,$T$3)) -> 0 | Q34: =MIN(1,(COUNTIF(M34:O34,$U$3)+COUNTIF(M34:O34,$U$4)+COUNTIF(M34:O34,$U$5))) -> 0 | R34: =SUMPRODUCT(COUNTIF(M34:O34,$V$3:$V$5)) -> 0
J35: Belarus | L35: =L34+1 -> 30 | M35: Sweden | N35: Portugal | O35: China | P35: =MIN(1,COUNTIF(M35:O35,$T$3)) -> 0 | Q35: =MIN(1,(COUNTIF(M35:O35,$U$3)+COUNTIF(M35:O35,$U$4)+COUNTIF(M35:O35,$U$5))) -> 0 | R35: =SUMPRODUCT(COUNTIF(M35:O35,$V$3:$V$5)) -> 0
... J101: Ireland | L101: =L100+1 -> 96 | M101: China | N101: China | O101: China | P101: =MIN(1,COUNTIF(M101:O101,$T$3)) -> 0 | Q101: =MIN(1,(COUNTIF(M101:O101,$U$3)+COUNTIF(M101:O101,$U$4)+COUNTIF(M101:O101,$U$5))) -> 0 | R101: =SUMPRODUCT(COUNTIF(M101:O101,$V$3:$V$5)) -> 0
J102: Israel
J103: Isle of Man
J104: India
J105: British Indian Ocean Territory
J106: Iraq
J107: Iran
J108: Iceland
J109: Italy
J110: Jersey
J111: Jamaica
J112: Jordan
J113: Japan
... J246: Zimbabwe

Sheet TEXT
A1: Function
A2: LEN | B2: =LEN(C2) -> 6 | C2: 123456
A3: LEFT | B3: =LEFT(C3,D3) -> hel | C3: hello | D3: 3
A4: RIGHT | B4: =RIGHT(C4,D4) -> llo | C4: hello | D4: 3
A5: MID | B5: =MID(C5,D5,E5) -> ell | C5: hello | D5: 2 | E5: 3
A6: PROPER | B6: =PROPER(C6) -> Hello There | C6: hello there
A7: UPPER | B7: =UPPER(C7) -> HELLO | C7: hello
A8: LOWER | B8: =LOWER(C8) -> hello | C8: HELLO
A9: TRUNC | B9: =TRUNC(C9,2) -> 1234.25 | C9: 1234.2564
A10: SEARCH | B10: =SEARCH(D10,C10,1) -> 1 | C10: hello | D10: he
A11: FIND | B11: =FIND(D11,C11,1) -> 2 | C11: hello | D11: ello | E11: <-The main difference between FIND and SEARCH is that FIND is case sensitive while SEARCH is not. Search also allows the use of wildcards when searching.
A12: SUBSTITUTE | B12: =SUBSTITUTE(C12,"m","g") -> g12 | C12: m12 | D12: <-substitutes a portion of a string with another string. If there are multiple instances of the string portion, you can identify which instances should be substituted.
A13: REPLACE | B13: =REPLACE(C13,2,3,"hi!") -> ahi!34567 | C13: am1234567 | D13: <-replaces a portion of a string with another string/number, where the portion to be replaced is identified by finding the starting point and the length of the string
A15: Exercise: Using the functions we discussed build a formula that outputs: "Happy Halloween" by manipulating the following string
A16: Happy Belated Halloween
A18: Using SUBSTITUTE:
A19: Using REPLACE:
A21: Exercise 2: Output "Happy Halloween" regardless of the word in between "Happy" and "Halloween"
A23: Using LEFT AND RIGHT:
A25: Other approaches that may come in handy
A26: =SEARCH(" ",A16,1) -> 6 | B26: SEARCH for first space starting in the first position
A27: =SEARCH(" ",A16,A26+1) -> 14 | B27: SEARCH for second space
A28: =A27-A26 -> 8 | B28: Number of characters between the 2 spaces
A31: Using multiple steps or formulas:
A32: =SEARCH(" ",A16,1) -> 6 | B32: SEARCH for first space starting in the first position
A33: =SEARCH(" ",A16,A32+1) -> 14 | B33: SEARCH for second space
A34: =LEFT(A16,A32) -> Happy | B34: LEFT (Happy has a space after it)
A35: =RIGHT(A16,LEN(A16)-A33) -> Halloween | B35: RIGHT w LEN
B36: Combine

Sheet TEXT_ans
A1: Function
A2: LEN | B2: =LEN(C2) -> 6 | C2: 123456
A3: LEFT | B3: =LEFT(C3,D3) -> hel | C3: hello | D3: 3
A4: RIGHT | B4: =RIGHT(C4,D4) -> llo | C4: hello | D4: 3
A5: MID | B5: =MID(C5,D5,E5) -> ell | C5: hello | D5: 2 | E5: 3
A6: PROPER | B6: =PROPER(C6) -> Hello There | C6: hello there
A7: UPPER | B7: =UPPER(C7) -> HELLO | C7: hello
A8: LOWER | B8: =LOWER(C8) -> hello | C8: HELLO
A9: TRUNC | B9: =TRUNC(C9,2) -> 1234.25 | C9: 1234.2564
A10: SEARCH | B10: =SEARCH(D10,C10,1) -> 1 | C10: hello | D10: he
A11: FIND | B11: =FIND(D11,C11,1) -> 2 | C11: hello | D11: ello | E11: <-The main difference between FIND and SEARCH is that FIND is case sensitive while SEARCH is not. Search also allows the use of wildcards when searching.
A12: SUBSTITUTE | B12: =SUBSTITUTE(C12,"m","g") -> g12 | C12: m12 | D12: <-substitutes a portion of a string with another string. If there are multiple instances of the string portion, you can identify which instances should be substituted.
A13: REPLACE | B13: =REPLACE(C13,2,3,"hi!") -> ahi!34567 | C13: am1234567 | D13: <-replaces a portion of a string with another string/number, where the portion to be replaced is identified by finding the starting point and the length of the string
A15: Exercise: Using the functions we discussed build a formula that outputs: "Happy Halloween" by manipulating the following string
A16: Happy Belated Halloween
A18: Using SUBSTITUTE: | B18: =SUBSTITUTE(A16,"Belated ","") -> Happy Halloween
A19: Using REPLACE: | B19: =REPLACE(A16,6,8,"") -> Happy Halloween
A21: Exercise 2: Output "Happy Halloween" regardless of the word in between "Happy" and "Halloween"
A23: Using LEFT AND RIGHT: | B23: =LEFT(A16,6)&RIGHT(A16,9) -> Happy Halloween
A25: Other approaches that may come in handy
A26: =SEARCH(" ",A16,1) -> 6 | B26: SEARCH for first space starting in the first position
A27: =SEARCH(" ",A16,A26+1) -> 14 | B27: SEARCH for second space
A28: =A27-A26 -> 8 | B28: Number of characters between the 2 spaces
A29: =REPLACE(A16,SEARCH(" ",A16,1),A28,"") -> Happy Halloween
A31: Using multiple steps or formulas:
A32: =SEARCH(" ",A16,1) -> 6 | B32: SEARCH for first space starting in the first position
A33: =SEARCH(" ",A16,A32+1) -> 14 | B33: SEARCH for second space
A34: =LEFT(A16,A32) -> Happy | B34: LEFT (Happy has a space after it)
A35: =RIGHT(A16,LEN(A16)-A33) -> Halloween | B35: RIGHT w LEN
A36: =A34&A35 -> Happy Halloween | B36: Combine

Sheet INDIRECT and &
B1: EBITDA
A2: 2014 | B2: 125
A3: =A2+1 -> 2015 | B3: =B2*1.06 -> 132.5
A4: =A3+1 -> 2016 | B4: =B3*1.07 -> 141.775
A5: =A4+1 -> 2017 | B5: =B4*1.06 -> 150.2815
A6: =A5+1 -> 2018 | B6: =B5*1.07 -> 160.80121
A7: =A6+1 -> 2019 | B7: =B6*1.06 -> 170.44928
A8: =A7+1 -> 2020 | B8: =B7*1.06 -> 180.67623
A9: =A8+1 -> 2021 | B9: =B8*1.06 -> 191.51681
A10: =A9+1 -> 2022 | B10: =B9*1.06 -> 203.00782
A11: =A10+1 -> 2023 | B11: =B10*1.06 -> 215.18829
A13: Pick a start year:
A14: Pick an end year:
A16: ="Cumulative EBITDA from "&B13&" to "&B14&":" -> Cumulative EBITDA from to :

Sheet INDIRECT and & _ans
B1: EBITDA
A2: 2014 | B2: 125
A3: =A2+1 -> 2015 | B3: =B2*1.06 -> 132.5
A4: =A3+1 -> 2016 | B4: =B3*1.07 -> 141.775
A5: =A4+1 -> 2017 | B5: =B4*1.06 -> 150.2815
A6: =A5+1 -> 2018 | B6: =B5*1.07 -> 160.80121
A7: =A6+1 -> 2019 | B7: =B6*1.06 -> 170.44928
A8: =A7+1 -> 2020 | B8: =B7*1.06 -> 180.67623
A9: =A8+1 -> 2021 | B9: =B8*1.06 -> 191.51681
A10: =A9+1 -> 2022 | B10: =B9*1.06 -> 203.00782
A11: =A10+1 -> 2023 | B11: =B10*1.06 -> 215.18829
A13: Pick a start year: | B13: 2016
A14: Pick an end year: | B14: 2021
A16: ="Cumulative EBITDA from "&B13&" to "&B14&":" -> Cumulative EBITDA from 2016 to 2021: | B16: =SUM(INDIRECT("B"&B13-2012&":B"&B14-2012)) -> 995.50002

Sheet Sort Filter  & Subtotal
B2: Sort the following table by industry, and then by market cap, in descending order
B4: Industry | C4: Company | D4: Ticker | E4: Share price | F4: Shares out. | G4: LTM Revenue | H4: LTM EBITDA | I4: Market cap.
B5: Energy | C5: Exxon Mobil | D5: wmt | E5: 94.01 | F5: 4320000000 | G5: 393720000000 | H5: 60950000000 | I5: 406123200000
B6: Tech | C6: Apple | D6: xom | E6: 536.09 | F6: 891990000 | G6: 173990000000 | H6: 56560000000 | I6: 478186919100
B7: Consumer | C7: Procter & Gamble | D7: tw | E7: 78.95 | F7: 2710000000 | G7: 84740000000 | H7: 19370000000 | I7: 213954500000
B8: Tech | C8: Google | D8: pg | E8: 1199.99 | F8: 336050000 | G8: 59820000000 | H8: 18030000000 | I8: 403256639500
B9: Telecom | C9: Cisco | D9: kmb | E9: 21.61 | F9: 5150000000 | G9: 47870000000 | H9: 12980000000 | I9: 111291500000
B10: Consumer | C10: Colgate | D10: csco | E10: 63.29 | F10: 918940000 | G10: 17420000000 | H10: 4560000000 | I10: 58159712600
B11: Consumer | C11: Kimberly Clark | D11: kmb | E11: 109.05 | F11: 379400000 | G11: 21150000000 | H11: 4.27e+09 | I11: 41373570000
B12: Industrials | C12: Alcoa | D12: aa | E12: 12.19 | F12: 1080000000 | G12: 23030000000 | H12: 2560000000 | I12: 13165200000
B13: Retail | C13: Safeway | D13: goog | E13: 38.65 | F13: 227870000 | G13: 36140000000 | H13: 1590000000 | I13: 8807175500
B14: Tech | C14: Yahoo | D14: cl | E14: 37.56 | F14: 1010000000 | G14: 4680000000 | H14: 1030000000 | I14: 37935600000
B15: Consulting | C15: Juniper | D15: msft | E15: 114.22 | F15: 70530000 | G15: 3590000000 | H15: 653890000 | I15: 8055936600
B16: Real Estate | C16: BRE Properties | D16: yhoo | E16: 61.565 | F16: 77300000 | G16: 404650000 | H16: 257310000 | I16: 4758974500
... B19: Banking | C19: Goldman Sachs | D19: gs | E19: 169.89 | F19: 467360000 | G19: 34210000000 | H19: 0 | I19: 79399790400
B21: Industry | C21: Company | D21: Ticker | E21: Share price | F21: Shares out. | G21: LTM Revenue | H21: LTM EBITDA | I21: Market cap.
B22: Banking | C22: Goldman Sachs | D22: gs | E22: 169.89 | F22: 467360000 | G22: 34210000000 | H22: 0 | I22: 79399790400
B23: Banking Total | I23: =SUBTOTAL(9,I22:I22) -> 79399790400
B24: Consulting | C24: Juniper | D24: msft | E24: 114.22 | F24: 70530000 | G24: 3590000000 | H24: 653890000 | I24: 8055936600
B25: Consulting Total | I25: =SUBTOTAL(9,I24:I24) -> 8055936600
B26: Consumer | C26: Procter & Gamble | D26: tw | E26: 78.95 | F26: 2710000000 | G26: 84740000000 | H26: 19370000000 | I26: 213954500000
B27: Consumer | C27: Colgate | D27: csco | E27: 63.29 | F27: 918940000 | G27: 17420000000 | H27: 4560000000 | I27: 58159712600
B28: Consumer | C28: Kimberly Clark | D28: kmb | E28: 109.05 | F28: 379400000 | G28: 21150000000 | H28: 4.27e+09 | I28: 41373570000
B29: Consumer Total | I29: =SUBTOTAL(9,I26:I28) -> 313487782600
B30: Energy | C30: Exxon Mobil | D30: wmt | E30: 94.01 | F30: 4320000000 | G30: 393720000000 | H30: 60950000000 | I30: 406123200000
B31: Energy Total | I31: =SUBTOTAL(9,I30:I30) -> 406123200000
B32: Industrials | C32: Alcoa | D32: aa | E32: 12.19 | F32: 1080000000 | G32: 23030000000 | H32: 2560000000 | I32: 13165200000
B33: Industrials Total | I33: =SUBTOTAL(9,I32:I32) -> 13165200000
B34: Real Estate | C34: BRE Properties | D34: yhoo | E34: 61.565 | F34: 77300000 | G34: 404650000 | H34: 257310000 | I34: 4758974500
B35: Real Estate Total | I35: =SUBTOTAL(9,I34:I34) -> 4758974500
B36: Retail | C36: Safeway | D36: goog | E36: 38.65 | F36: 227870000 | G36: 36140000000 | H36: 1590000000 | I36: 8807175500
B37: Retail Total | I37: =SUBTOTAL(9,I36:I36) -> 8807175500
B38: Tech | C38: Apple | D38: xom | E38: 536.09 | F38: 891990000 | G38: 173990000000 | H38: 56560000000 | I38: 478186919100
B39: Tech | C39: Google | D39: pg | E39: 1199.99 | F39: 336050000 | G39: 59820000000 | H39: 18030000000 | I39: 403256639500
B40: Tech | C40: Yahoo | D40: cl | E40: 37.56 | F40: 1010000000 | G40: 4680000000 | H40: 1030000000 | I40: 37935600000
B41: Tech | C41: Zynga | D41: znga | E41: 5.65 | F41: 876880000 | G41: 873270000 | H41: 73630000 | I41: 4954372000
B42: Tech Total | I42: =SUBTOTAL(9,I38:I41) -> 924333530600
B43: Telecom | C43: Cisco | D43: kmb | E43: 21.61 | F43: 5150000000 | G43: 47870000000 | H43: 12980000000 | I43: 111291500000
B44: Telecom | C44: Logmein | D44: logm | E44: 44.21 | F44: 24190000 | G44: 166260000 | H44: 7470000 | I44: 1069439900
B45: Telecom Total | I45: =SUBTOTAL(9,I43:I44) -> 112360939900
B46: Grand Total | I46: =SUBTOTAL(9,I22:I44) -> 1870492530100

Sheet PT Input
A1: REIT | B1: Property Type | C1: Region | D1: Sq. Ft. | E1: Property Value ($ in 000's) | G1: Build a pivot table to answer the following questions | N1: Answers
A2: BRE Properties | B2: Residential | C2: East | D2: 5800 | E2: 1391 | G2: Which region shows the most overall property sales, by square footage?
A3: Capital Properties | B3: Retail | C3: West | D3: 2000 | E3: 845 | G3: Which region shows the most Leisure sales, by square footage?
A4: Equity Residential | B4: Office | C4: North | D4: 6558 | E4: 1391 | G4: Which region(s) have zero Leisure property sales?
A5: Equity Residential | B5: Leisure | C5: South | D5: 8683 | E5: 1823 | G5: In which region does BRE appear to have properties valued significantly above its peers?
A6: Capital Properties | B6: Residential | C6: South | D6: 769 | E6: 280 | G6: By looking at the Pivot Table that is not broken down by region, which property type appears to be Capital Properties’s weakest in terms of value?
A7: BRE Properties | B7: Retail | C7: East | D7: 3900 | E7: 1174 | G7: Which REIT has the highest value real estate, in dollars?
A8: BRE Properties | B8: Office | C8: North | D8: 980 | E8: 680 | G8: Which REIT has the lowest number of retail properties?
A9: Capital Properties | B9: Retail | C9: North | D9: 4000 | E9: 1887 | G9: What was the total value of Office real estate that Equity Residential sold in the South?
A10: Capital Properties | B10: Office | C10: North | D10: 3850 | E10: 1724 | G10: Which property type is the most popular (by number of properties) in the South?
A11: Equity Residential | B11: Retail | C11: South | D11: 450 | E11: 346 | G11: What is the % of Equity Residential properties (by number of properties) as a % total properties in the South?
A12: BRE Properties | B12: Office | C12: East | D12: 6000 | E12: 1355
A13: Capital Properties | B13: Leisure | C13: West | D13: 826 | E13: 869
A14: Equity Residential | B14: Retail | C14: West | D14: 5401 | E14: 1644
A15: Equity Residential | B15: Office | C15: East | D15: 4392 | E15: 1904
A16: Capital Properties | B16: Office | C16: North | D16: 2974 | E16: 1267
A17: BRE Properties | B17: Leisure | C17: South | D17: 1429 | E17: 1563
A18: BRE Properties | B18: Leisure | C18: South | D18: 2590 | E18: 1005
A19: Capital Properties | B19: Residential | C19: North | D19: 1511 | E19: 959
A20: BRE Properties | B20: Leisure | C20: West | D20: 2234 | E20: 1246
A21: Equity Residential | B21: Residential | C21: East | D21: 1928 | E21: 1223
A22: Capital Properties | B22: Residential | C22: South | D22: 4898 | E22: 1667
A23: BRE Properties | B23: Leisure | C23: North | D23: 4200 | E23: 1250
... A55: Capital Properties | B55: Retail | C55: East | D55: 4069 | E55: 1965

Sheet PT Input_ans
A1: REIT | B1: Property Type | C1: Region | D1: Sq. Ft. | E1: Property Value ($ in 000's) | G1: Build a pivot table to answer the following questions | N1: Answers
A2: BRE Properties | B2: Residential | C2: East | D2: 5800 | E2: 1391 | G2: Which region shows the most overall property sales, by square footage? | N2: East
A3: Capital Properties | B3: Retail | C3: West | D3: 2000 | E3: 845 | G3: Which region shows the most Leisure sales, by square footage? | N3: South
A4: Equity Residential | B4: Office | C4: North | D4: 6558 | E4: 1391 | G4: Which region(s) have zero Leisure property sales? | N4: East
A5: Equity Residential | B5: Leisure | C5: South | D5: 8683 | E5: 1823 | G5: In which region does BRE appear to have properties valued significantly above its peers? | N5: East
A6: Capital Properties | B6: Residential | C6: South | D6: 769 | E6: 280 | G6: By looking at the Pivot Table that is not broken down by region, which property type appears to be Capital Properties’s weakest in terms of value? | N6: Leisure
A7: BRE Properties | B7: Retail | C7: East | D7: 3900 | E7: 1174 | G7: Which REIT has the highest value real estate, in dollars? | N7: Equity Residential
A8: BRE Properties | B8: Office | C8: North | D8: 980 | E8: 680 | G8: Which REIT has the lowest number of retail properties? | N8: BRE Properties
A9: Capital Properties | B9: Retail | C9: North | D9: 4000 | E9: 1887 | G9: What was the total value of Office real estate that Equity Residential sold in the South? | N9: 1752
A10: Capital Properties | B10: Office | C10: North | D10: 3850 | E10: 1724 | G10: Which property type is the most popular (by number of properties) in the South? | N10: Residential
A11: Equity Residential | B11: Retail | C11: South | D11: 450 | E11: 346 | G11: What is the % of Equity Residential properties (by number of properties) as a % total properties in the South? | N11: 0.2857
A12: BRE Properties | B12: Office | C12: East | D12: 6000 | E12: 1355
A13: Capital Properties | B13: Leisure | C13: West | D13: 826 | E13: 869 | G13: Count of Property Value | H13: Column Labels
A14: Equity Residential | B14: Retail | C14: West | D14: 5401 | E14: 1644 | G14: Row Labels | H14: East | I14: North | J14: South | K14: West | L14: Grand Total
A15: Equity Residential | B15: Office | C15: East | D15: 4392 | E15: 1904 | G15: BRE Properties | H15: 0.57142857 | I15: 0.25 | J15: 0.28571429 | K15: 0.1 | L15: 0.31481481
A16: Capital Properties | B16: Office | C16: North | D16: 2974 | E16: 1267 | G16: Capital Properties | H16: 0.21428571 | I16: 0.375 | J16: 0.42857143 | K16: 0.4 | L16: 0.35185185
A17: BRE Properties | B17: Leisure | C17: South | D17: 1429 | E17: 1563 | G17: Equity Residential | H17: 0.21428571 | I17: 0.375 | J17: 0.28571429 | K17: 0.5 | L17: 0.33333333
A18: BRE Properties | B18: Leisure | C18: South | D18: 2590 | E18: 1005 | G18: Grand Total | H18: 1 | I18: 1 | J18: 1 | K18: 1 | L18: 1
A19: Capital Properties | B19: Residential | C19: North | D19: 1511 | E19: 959
A20: BRE Properties | B20: Leisure | C20: West | D20: 2234 | E20: 1246
A21: Equity Residential | B21: Residential | C21: East | D21: 1928 | E21: 1223
A22: Capital Properties | B22: Residential | C22: South | D22: 4898 | E22: 1667
A23: BRE Properties | B23: Leisure | C23: North | D23: 4200 | E23: 1250
A24: Equity Residential | B24: Residential | C24: North | D24: 1785 | E24: 1034
A25: Capital Properties | B25: Residential | C25: South | D25: 1100 | E25: 642
A26: Capital Properties | B26: Retail | C26: West | D26: 3214 | E26: 1200
A27: BRE Properties | B27: Office | C27: East | D27: 2931 | E27: 1827
A28: Equity Residential | B28: Office | C28: South | D28: 4875 | E28: 1752
A29: Equity Residential | B29: Leisure | C29: North | D29: 3165 | E29: 1271
A30: Capital Properties | B30: Residential | C30: North | D30: 726 | E30: 418
... A55: Capital Properties | B55: Retail | C55: East | D55: 4069 | E55: 1965

Sheet CF
A1: Conditional formatting (alt O D)
B3: Exercise 1: Sales Results | H3: Exercise 2: Historical vs Projected Results
B4: 1. Highlight sales in the top 10% | H4: Given current year, color all rows in prior years
B5: 2. Highlight entire row where sales were above: | F5: 30000 | H5: Current year: | K5: 2018
B7: Date | C7: Salesrep | D7: Sales | E7: Region | F7: Year
B8: 39436 | C8: Amanda | D8: 29688 | E8: Canada | F8: 2007 | I8: 2014 | J8: =I8+1 -> 2015 | K8: =J8+1 -> 2016 | L8: =K8+1 -> 2017 | M8: =L8+1 -> 2018 | N8: =M8+1 -> 2019
B9: 39496 | C9: Barry | D9: 37812 | E9: Canada | F9: 2008 | H9: Revenues | I9: 100 | J9: =I9*1.1 -> 110 | K9: =J9*1.1 -> 121 | L9: =K9*1.1 -> 133.1 | M9: =L9*1.1 -> 146.41 | N9: =M9*1.1 -> 161.051
B10: 39179 | C10: Sara | D10: 6804 | E10: Latin America | F10: 2007 | H10: Expenses | I10: =I9*0.55 -> 55 | J10: =J9*0.55 -> 60.5 | K10: =K9*0.55 -> 66.55 | L10: =L9*0.55 -> 73.205 | M10: =M9*0.55 -> 80.5255 | N10: =N9*0.55 -> 88.57805
B11: 39508 | C11: John | D11: 14867 | E11: USA | F11: 2008
B12: 38965 | C12: Barry | D12: 29406 | E12: Canada | F12: 2006
B13: 38785 | C13: John | D13: 35784 | E13: Latin America | F13: 2006 | H13: Exercise 3: Stock screen
B14: 39181 | C14: Barry | D14: 30005 | E14: USA | F14: 2007 | H14: Beta less than: | L14: 2
B15: 39418 | C15: John | D15: 37033 | E15: Mexico | F15: 2007 | H15: ROE greater than: | L15: 0.15
B16: 38805 | C16: John | D16: 23106 | E16: USA | F16: 2006 | H16: Highlight rows that meet criteria
B17: 39373 | C17: John | D17: 9910 | E17: Latin America | F17: 2007
B18: 38765 | C18: Barry | D18: 11012 | E18: Canada | F18: 2006 | H18: Stock | I18: Beta | J18: ROE | K18: PE | L18: DP
B19: 39236 | C19: Sara | D19: 8032 | E19: Canada | F19: 2007 | H19: 1 | I19: -1 | J19: 0.15 | K19: 13 | L19: 0.08
B20: 39162 | C20: Sara | D20: 10112 | E20: Canada | F20: 2007 | H20: 2 | I20: -2 | J20: 0 | K20: 13 | L20: 0.02
B21: 39269 | C21: John | D21: 24643 | E21: Canada | F21: 2007 | H21: 3 | I21: -2 | J21: 0.1 | K21: 13 | L21: 0
B22: 39434 | C22: Amanda | D22: 25876 | E22: Mexico | F22: 2007 | H22: 4 | I22: 1 | J22: 0.03 | K22: 14 | L22: 0.03
B23: 39394 | C23: John | D23: 25627 | E23: Latin America | F23: 2007 | H23: 5 | I23: -1 | J23: 0.09 | K23: 8 | L23: 0.02
B24: 39435 | C24: John | D24: 13656 | E24: Latin America | F24: 2007 | H24: 6 | I24: 3 | J24: 0.31 | K24: 10 | L24: 0.03
B25: 39552 | C25: Barry | D25: 16159 | E25: Canada | F25: 2008 | H25: 7 | I25: 1 | J25: 0.23 | K25: 9 | L25: 0.05
B26: 39108 | C26: John | D26: 22918 | E26: USA | F26: 2007 | H26: 8 | I26: -2 | J26: 0.07 | K26: 13 | L26: 0.07
B27: 39382 | C27: Amanda | D27: 18825 | E27: USA | F27: 2007 | H27: 9 | I27: -2 | J27: 0.22 | K27: 7 | L27: 0.01
B28: 38986 | C28: Amanda | D28: 17893 | E28: Mexico | F28: 2006 | H28: 10 | I28: 3 | J28: 0.35 | K28: 12 | L28: 0.05
B29: 39540 | C29: Barry | D29: 35667 | E29: Mexico | F29: 2008 | H29: 11 | I29: -2 | J29: 0.27 | K29: 14 | L29: 0
B30: 39200 | C30: Sara | D30: 8538 | E30: Mexico | F30: 2007 | H30: 12 | I30: 4 | J30: 0.09 | K30: 7 | L30: 0.01
... B68: 39155 | C68: John | D68: 29641 | E68: Mexico | F68: 2007 | H68: 50 | I68: 0 | J68: 0.12 | K68: 10 | L68: 0.04
B69: 39135 | C69: Barry | D69: 10953 | E69: Latin America | F69: 2007
B70: 39152 | C70: Sara | D70: 17379 | E70: Mexico | F70: 2007
B71: 39053 | C71: John | D71: 18451 | E71: Canada | F71: 2006
B72: 38989 | C72: Sara | D72: 13605 | E72: Latin America | F72: 2006
B73: 39581 | C73: John | D73: 30500 | E73: USA | F73: 2008
B74: 39594 | C74: Barry | D74: 21955 | E74: Canada | F74: 2008
B75: 39545 | C75: Sara | D75: 37154 | E75: Canada | F75: 2008
B76: 38973 | C76: Barry | D76: 27567 | E76: Latin America | F76: 2006
B77: 39117 | C77: John | D77: 30918 | E77: Canada | F77: 2007
B78: 38818 | C78: Amanda | D78: 17335 | E78: Mexico | F78: 2006
B79: 39276 | C79: Amanda | D79: 35432 | E79: Canada | F79: 2007
B80: 38779 | C80: Barry | D80: 35341 | E80: Canada | F80: 2006
... B1158: 38820 | C1158: Sara | D1158: 31130 | E1158: USA | F1158: 2006

Sheet CF_ ans
A1: Conditional formatting (alt O D)
B3: Exercise 1: Sales Results | H3: Exercise 2: Historical vs Projected Results
B4: 1. Highlight sales in the top 10% | H4: Given current year, color all rows in prior years
B5: 2. Highlight entire row where sales were above: | F5: 30000 | H5: Current year: | K5: 2018
B7: Date | C7: Salesrep | D7: Sales | E7: Region | F7: Year
B8: 39436 | C8: Amanda | D8: 29688 | E8: Canada | F8: 2007 | I8: 2014 | J8: =I8+1 -> 2015 | K8: =J8+1 -> 2016 | L8: =K8+1 -> 2017 | M8: =L8+1 -> 2018 | N8: =M8+1 -> 2019
B9: 39496 | C9: Barry | D9: 37812 | E9: Canada | F9: 2008 | H9: Revenues | I9: 100 | J9: =I9*1.1 -> 110 | K9: =J9*1.1 -> 121 | L9: =K9*1.1 -> 133.1 | M9: =L9*1.1 -> 146.41 | N9: =M9*1.1 -> 161.051
B10: 39179 | C10: Sara | D10: 6804 | E10: Latin America | F10: 2007 | H10: Expenses | I10: =I9*0.55 -> 55 | J10: =J9*0.55 -> 60.5 | K10: =K9*0.55 -> 66.55 | L10: =L9*0.55 -> 73.205 | M10: =M9*0.55 -> 80.5255 | N10: =N9*0.55 -> 88.57805
B11: 39508 | C11: John | D11: 14867 | E11: USA | F11: 2008
B12: 38965 | C12: Barry | D12: 29406 | E12: Canada | F12: 2006
B13: 38785 | C13: John | D13: 35784 | E13: Latin America | F13: 2006 | H13: Exercise 3: Stock screen
B14: 39181 | C14: Barry | D14: 30005 | E14: USA | F14: 2007 | H14: Beta less than: | L14: 2
B15: 39418 | C15: John | D15: 37033 | E15: Mexico | F15: 2007 | H15: ROE greater than: | L15: 0.15
B16: 38805 | C16: John | D16: 23106 | E16: USA | F16: 2006 | H16: Highlight rows that meet criteria
B17: 39373 | C17: John | D17: 9910 | E17: Latin America | F17: 2007
B18: 38765 | C18: Barry | D18: 11012 | E18: Canada | F18: 2006 | H18: Stock | I18: Beta | J18: ROE | K18: PE | L18: DP
B19: 39236 | C19: Sara | D19: 8032 | E19: Canada | F19: 2007 | H19: 1 | I19: -1 | J19: 0.15 | K19: 13 | L19: 0.08
B20: 39162 | C20: Sara | D20: 10112 | E20: Canada | F20: 2007 | H20: 2 | I20: -2 | J20: 0 | K20: 13 | L20: 0.02
B21: 39269 | C21: John | D21: 24643 | E21: Canada | F21: 2007 | H21: 3 | I21: -2 | J21: 0.1 | K21: 13 | L21: 0
B22: 39434 | C22: Amanda | D22: 25876 | E22: Mexico | F22: 2007 | H22: 4 | I22: 1 | J22: 0.03 | K22: 14 | L22: 0.03
B23: 39394 | C23: John | D23: 25627 | E23: Latin America | F23: 2007 | H23: 5 | I23: -1 | J23: 0.09 | K23: 8 | L23: 0.02
B24: 39435 | C24: John | D24: 13656 | E24: Latin America | F24: 2007 | H24: 6 | I24: 3 | J24: 0.31 | K24: 10 | L24: 0.03
B25: 39552 | C25: Barry | D25: 16159 | E25: Canada | F25: 2008 | H25: 7 | I25: 1 | J25: 0.23 | K25: 9 | L25: 0.05
B26: 39108 | C26: John | D26: 22918 | E26: USA | F26: 2007 | H26: 8 | I26: -2 | J26: 0.07 | K26: 13 | L26: 0.07
B27: 39382 | C27: Amanda | D27: 18825 | E27: USA | F27: 2007 | H27: 9 | I27: -2 | J27: 0.22 | K27: 7 | L27: 0.01
B28: 38986 | C28: Amanda | D28: 17893 | E28: Mexico | F28: 2006 | H28: 10 | I28: 3 | J28: 0.35 | K28: 12 | L28: 0.05
B29: 39540 | C29: Barry | D29: 35667 | E29: Mexico | F29: 2008 | H29: 11 | I29: -2 | J29: 0.27 | K29: 14 | L29: 0
B30: 39200 | C30: Sara | D30: 8538 | E30: Mexico | F30: 2007 | H30: 12 | I30: 4 | J30: 0.09 | K30: 7 | L30: 0.01
... B68: 39155 | C68: John | D68: 29641 | E68: Mexico | F68: 2007 | H68: 50 | I68: 0 | J68: 0.12 | K68: 10 | L68: 0.04
B69: 39135 | C69: Barry | D69: 10953 | E69: Latin America | F69: 2007
B70: 39152 | C70: Sara | D70: 17379 | E70: Mexico | F70: 2007
B71: 39053 | C71: John | D71: 18451 | E71: Canada | F71: 2006
B72: 38989 | C72: Sara | D72: 13605 | E72: Latin America | F72: 2006
B73: 39581 | C73: John | D73: 30500 | E73: USA | F73: 2008
B74: 39594 | C74: Barry | D74: 21955 | E74: Canada | F74: 2008
B75: 39545 | C75: Sara | D75: 37154 | E75: Canada | F75: 2008
B76: 38973 | C76: Barry | D76: 27567 | E76: Latin America | F76: 2006
B77: 39117 | C77: John | D77: 30918 | E77: Canada | F77: 2007
B78: 38818 | C78: Amanda | D78: 17335 | E78: Mexico | F78: 2006
B79: 39276 | C79: Amanda | D79: 35432 | E79: Canada | F79: 2007
B80: 38779 | C80: Barry | D80: 35341 | E80: Canada | F80: 2006
... B1158: 38820 | C1158: Sara | D1158: 31130 | E1158: USA | F1158: 2006

Sheet Custom text
B2: Negative number in parenthesis, aligned with positive number format
B3: Format | C3: #,##0.00_);(#,##0.00) | D3: This is also standard number format for most versions of Excel
B4: Positive number | C4: 1212.7
B5: Negative number aligned with positive | C5: -1212.7
B6: Zero | C6: 0 | D6: Since the third custom format field is empty, zeros are treated using positive format
B7: Text | C7: text | D7: Since the fourth custom format field is empty, zeros are treated as plain text
B9: Multiple "x" format. Negative numbers in parenthesis, aligned with positive number format
B10: Format | C10: _(#,###0.0x_);(##,##0.0x)
B11: Positive - Multiple | C11: 15
B12: Negative - Multiple | C12: -15
B14: Negative number in parenthesis, aligned with positive number format and multiple "x" format
B15: Format | C15: _(#,###0.0_x_);(##,##0.0)_x
B16: Positive - Multiple | C16: 15
B17: Negative - Multiple | C17: -15
B19: Negative number in parenthesis, aligned with positive number format, "Balance" when result is 0
B20: Format | C20: #,##0.00_);(#,##0.00);"Balance"
B21: Positive | C21: 5
B22: Negative number aligned with positive | C22: -4
B23: Zero | C23: 0
B25: Other formats
B26: 5 | C26: 0 "days"
B27: 300 | C27: L + 0 "bps"

Sheet Text to Columns Data
A1: Company CC last_name email country
A2: Rooxo 6.38151E+15 Crawford kcrawford0@wired.com Tokelau
A3: Demizz 3.55627E+15 Morrison emorrison1@amazon.de Tajikistan
A4: Zoomdog 4.91189E+15 Holmes cholmes2@imageshack.us Sudan
A5: Brightbean 3.04693E+13 Baker sbaker3@cornell.edu Mauritius
A6: Oyondu 5.10018E+15 Marshall amarshall4@hp.com Kuwait
A7: Eidel 4.50874E+15 Evans devans5@technorati.com Malta
A8: Zoonoodle 2.01751E+14 Myers amyers6@ustream.tv Bahrain
A9: Devcast 5.36343E+15 Bailey ebailey7@oaic.gov.au Romania
A10: Rhyzio 5.00236E+15 Perez cperez8@wix.com Slovenia
A11: Riffpedia 5.60222E+15 Jordan jjordan9@bravesites.com Rwanda
A12: Jaxworks 2.01755E+14 Sullivan jsullivana@weebly.com Swaziland
... A801: Brainverse 5.10013E+15 Robinson arobinsonm7@bing.com British Indian Ocean Territory

Sheet Dynamic headers & Misc
B2: Company Name: | C2: Apple
B3: Current Date: | C3: 41802
B5: Dynamic headers and TEXT
B6: Create dynamic header "Income Statement for [company inserted above]": | C6: ="Income Statement for "&C2 -> Income Statement for Apple
B7: Create dynamic row label "Share price as of [date inserted above]": | C7: ="Share price as of "&TEXT(C3,"mm/dd/yy") -> Share price as of 06/12/14 | F7: <- Use TEXT to improve header
B9: Custom formatting | C9: 5.0x
B10: Format number as a multiple | C10: 5
B11: Format 1 as "True" and 0 as "False" | C11: 5
B12: Convert any number n to say n "years" | C12: 6
B14: Alt Enter
B15: Present value, also known as present discounted value, is a future amount of money that has been discounted to reflect its current value, as if it existed today. The present value is always less than or equal to the future value because money has interest-earning potential, a characteristic referred to as the time value of money.

Sheet Printing
A1: Company | B1: Credit card | C1: Last Name | D1: Email | E1: Date | F1: FDA Code
A2: Rooxo | B2: 6.3815143e+15 | C2: Crawford | D2: kcrawford0@wired.com | E2: 42422 | F2: 76439-122
A3: Demizz | B3: 3.5562708e+15 | C3: Morrison | D3: emorrison1@amazon.de | E3: 42215 | F3: 52125-087
A4: Zoomdog | B4: 4.91189e+15 | C4: Holmes | D4: cholmes2@imageshack.us | E4: 42221 | F4: 0179-0083
A5: Brightbean | B5: 30469336552667 | C5: Baker | D5: sbaker3@cornell.edu | E5: 42405 | F5: 53489-149
A6: Oyondu | B6: 5.1001759e+15 | C6: Marshall | D6: amarshall4@hp.com | E6: 42307 | F6: 63187-023
A7: Eidel | B7: 4.5087392e+15 | C7: Evans | D7: devans5@technorati.com | E7: 42426 | F7: 41250-380
A8: Zoonoodle | B8: 201750521290020 | C8: Myers | D8: amyers6@ustream.tv | E8: 42391 | F8: 53808-0661
A9: Devcast | B9: 5.3634302e+15 | C9: Bailey | D9: ebailey7@oaic.gov.au | E9: 42231 | F9: 41520-193
A10: Rhyzio | B10: 5.0023563e+15 | C10: Perez | D10: cperez8@wix.com | E10: 42216 | F10: 0409-2066
A11: Riffpedia | B11: 5.602221e+15 | C11: Jordan | D11: jjordan9@bravesites.com | E11: 42155 | F11: 51079-782
A12: Jaxworks | B12: 201755343992703 | C12: Sullivan | D12: jsullivana@weebly.com | E12: 42244 | F12: 33992-1403
A13: Realblab | B13: 3.5891214e+15 | C13: Crawford | D13: dcrawfordb@usatoday.com | E13: 42361 | F13: 63629-2981
... A1001: Dabtype | B1001: 5.602245e+16 | C1001: Nichols | D1001: gnicholsrr@wordpress.com | E1001: 42342 | F1001: 55154-7468

Sheet Dates
A1: Transaction ID | B1: Transaction date | C1: Fiscal half | AE1: Fiscal Half Date - Approach #1 | AF1: Fiscal Half Date - Approach #2
A2: 12449 | B2: 42264 | C2: =EOMONTH(B2,6+6*(ROUND(MONTH(B2)/12,0))-MONTH(B2)-1) -> 42338 | AE2: =IF(AND(DAY(B2)<31,MONTH(B2)>5),CONCATENATE("11/30/"&YEAR(B2)),CONCATENATE("5/31/"&YEAR(B2))) -> 11/30/2015 | AF2: =EOMONTH(B2,6+6*(ROUND(MONTH(B2)/12,0))-MONTH(B2)-1) -> 42338
A3: 18920 | B3: 42251 | C3: =EOMONTH(B3,6+6*(ROUND(MONTH(B3)/12,0))-MONTH(B3)-1) -> 42338 | AE3: =IF(AND(DAY(B3)<31,MONTH(B3)>5),CONCATENATE("11/30/"&YEAR(B3)),CONCATENATE("5/31/"&YEAR(B3))) -> 11/30/2015 | AF3: =EOMONTH(B3,6+6*(ROUND(MONTH(B3)/12,0))-MONTH(B3)-1) -> 42338
A4: 10501 | B4: 42237 | C4: =EOMONTH(B4,6+6*(ROUND(MONTH(B4)/12,0))-MONTH(B4)-1) -> 42338 | AE4: =IF(AND(DAY(B4)<31,MONTH(B4)>5),CONCATENATE("11/30/"&YEAR(B4)),CONCATENATE("5/31/"&YEAR(B4))) -> 11/30/2015 | AF4: =EOMONTH(B4,6+6*(ROUND(MONTH(B4)/12,0))-MONTH(B4)-1) -> 42338
A5: 13852 | B5: 42233 | C5: =EOMONTH(B5,6+6*(ROUND(MONTH(B5)/12,0))-MONTH(B5)-1) -> 42338 | AE5: =IF(AND(DAY(B5)<31,MONTH(B5)>5),CONCATENATE("11/30/"&YEAR(B5)),CONCATENATE("5/31/"&YEAR(B5))) -> 11/30/2015 | AF5: =EOMONTH(B5,6+6*(ROUND(MONTH(B5)/12,0))-MONTH(B5)-1) -> 42338
A6: 13078 | B6: 42203 | C6: =EOMONTH(B6,6+6*(ROUND(MONTH(B6)/12,0))-MONTH(B6)-1) -> 42338 | AE6: =IF(AND(DAY(B6)<31,MONTH(B6)>5),CONCATENATE("11/30/"&YEAR(B6)),CONCATENATE("5/31/"&YEAR(B6))) -> 11/30/2015 | AF6: =EOMONTH(B6,6+6*(ROUND(MONTH(B6)/12,0))-MONTH(B6)-1) -> 42338
A7: 17087 | B7: 42187 | C7: =EOMONTH(B7,6+6*(ROUND(MONTH(B7)/12,0))-MONTH(B7)-1) -> 42338 | AE7: =IF(AND(DAY(B7)<31,MONTH(B7)>5),CONCATENATE("11/30/"&YEAR(B7)),CONCATENATE("5/31/"&YEAR(B7))) -> 11/30/2015 | AF7: =EOMONTH(B7,6+6*(ROUND(MONTH(B7)/12,0))-MONTH(B7)-1) -> 42338
A8: 17326 | B8: 42182 | C8: =EOMONTH(B8,6+6*(ROUND(MONTH(B8)/12,0))-MONTH(B8)-1) -> 42338 | AE8: =IF(AND(DAY(B8)<31,MONTH(B8)>5),CONCATENATE("11/30/"&YEAR(B8)),CONCATENATE("5/31/"&YEAR(B8))) -> 11/30/2015 | AF8: =EOMONTH(B8,6+6*(ROUND(MONTH(B8)/12,0))-MONTH(B8)-1) -> 42338
A9: 15347 | B9: 42181 | C9: =EOMONTH(B9,6+6*(ROUND(MONTH(B9)/12,0))-MONTH(B9)-1) -> 42338 | AE9: =IF(AND(DAY(B9)<31,MONTH(B9)>5),CONCATENATE("11/30/"&YEAR(B9)),CONCATENATE("5/31/"&YEAR(B9))) -> 11/30/2015 | AF9: =EOMONTH(B9,6+6*(ROUND(MONTH(B9)/12,0))-MONTH(B9)-1) -> 42338
A10: 18866 | B10: 42107 | C10: =EOMONTH(B10,6+6*(ROUND(MONTH(B10)/12,0))-MONTH(B10)-1) -> 42155 | AE10: =IF(AND(DAY(B10)<31,MONTH(B10)>5),CONCATENATE("11/30/"&YEAR(B10)),CONCATENATE("5/31/"&YEAR(B10))) -> 5/31/2015 | AF10: =EOMONTH(B10,6+6*(ROUND(MONTH(B10)/12,0))-MONTH(B10)-1) -> 42155
A11: 14547 | B11: 42085 | C11: =EOMONTH(B11,6+6*(ROUND(MONTH(B11)/12,0))-MONTH(B11)-1) -> 42155 | AE11: =IF(AND(DAY(B11)<31,MONTH(B11)>5),CONCATENATE("11/30/"&YEAR(B11)),CONCATENATE("5/31/"&YEAR(B11))) -> 5/31/2015 | AF11: =EOMONTH(B11,6+6*(ROUND(MONTH(B11)/12,0))-MONTH(B11)-1) -> 42155
A12: 12784 | B12: 42077 | C12: =EOMONTH(B12,6+6*(ROUND(MONTH(B12)/12,0))-MONTH(B12)-1) -> 42155 | AE12: =IF(AND(DAY(B12)<31,MONTH(B12)>5),CONCATENATE("11/30/"&YEAR(B12)),CONCATENATE("5/31/"&YEAR(B12))) -> 5/31/2015 | AF12: =EOMONTH(B12,6+6*(ROUND(MONTH(B12)/12,0))-MONTH(B12)-1) -> 42155
A13: 19808 | B13: 42067 | C13: =EOMONTH(B13,6+6*(ROUND(MONTH(B13)/12,0))-MONTH(B13)-1) -> 42155 | AE13: =IF(AND(DAY(B13)<31,MONTH(B13)>5),CONCATENATE("11/30/"&YEAR(B13)),CONCATENATE("5/31/"&YEAR(B13))) -> 5/31/2015 | AF13: =EOMONTH(B13,6+6*(ROUND(MONTH(B13)/12,0))-MONTH(B13)-1) -> 42155
... A57: 16304 | B57: 41275 | C57: =EOMONTH(B57,6+6*(ROUND(MONTH(B57)/12,0))-MONTH(B57)-1) -> 41425 | AE57: =IF(AND(DAY(B57)<31,MONTH(B57)>5),CONCATENATE("11/30/"&YEAR(B57)),CONCATENATE("5/31/"&YEAR(B57))) -> 5/31/2013 | AF57: =EOMONTH(B57,6+6*(ROUND(MONTH(B57)/12,0))-MONTH(B57)-1) -> 41425
